Entrega Final/divisor/control_div.v
module control_div (
    input  wire clk,
    input  wire rst,     
    input  wire start,
    input  wire msb_r, 
    input  wire z,     

    output reg  done,
    output reg  LDR,
    output reg  Q0,
    output reg  SH,
    output reg  LDQ,
    output reg  DECi
);

    localparam [2:0] START_ST   = 3'b000;
    localparam [2:0] CHECK_I_ST = 3'b001;
    localparam [2:0] SHIFT_ST   = 3'b010;
    localparam [2:0] CHECK_R_ST = 3'b011;
    localparam [2:0] ADD_ST     = 3'b100;
    localparam [2:0] DONE_ST    = 3'b101;

    reg [2:0] state, next_state;

    always @(posedge clk or posedge rst) begin
        if (rst)
            state <= START_ST;
        else
            state <= next_state;
    end

    always @(*) begin
        case (state)
            START_ST:   next_state = start ? CHECK_I_ST : START_ST;
            CHECK_I_ST: next_state = z     ? DONE_ST     : SHIFT_ST;
            SHIFT_ST:   next_state = CHECK_R_ST;
            CHECK_R_ST: next_state = msb_r ? ADD_ST      : CHECK_I_ST;
            ADD_ST:     next_state = CHECK_I_ST;
            DONE_ST:    next_state = START_ST;
            default:    next_state = START_ST;
        endcase
    end

    always @(*) begin
        done = 1'b0;
        LDR  = 1'b0;
        Q0   = 1'b0;
        SH   = 1'b0;
        LDQ  = 1'b0;
        DECi = 1'b0;
        case (state)
            START_ST: begin
                LDQ = 1'b1;
            end
            CHECK_I_ST: ; 
            SHIFT_ST: begin
                SH   = 1'b1;
                DECi = 1'b1;
            end
            CHECK_R_ST: ; 
            ADD_ST: begin
                LDR = 1'b1;
                Q0  = 1'b1;
            end
            DONE_ST: begin
                done = 1'b1;
            end
            default: ;
        endcase
    end

endmodule

Entrega Final/divisor/sumador_comp.v
module sumador_comp (
    input  wire [15:0] R,
    input  wire [15:0] V,
    output wire [15:0] diff,
    output wire         MSB_R
);

    wire [16:0] resta;

    assign resta = {1'b0, R} - {1'b0, V};
    assign diff  = resta[15:0];
    assign MSB_R = ~resta[16];   
endmodule

Entrega Final/divisor/comp_i.v
module comp_i (
    input  wire [4:0] i_count,
    output wire        z
);

    assign z = (i_count == 5'b0);

endmodule

Entrega Final/divisor/reg_i.v
module reg_i (
    input  wire       clk,
    input  wire       reset_i,  
    input  wire       dec,      
    output reg  [4:0] i_count
);

    localparam [4:0] N = 5'd16;

    always @(negedge clk) begin
        if (reset_i)
            i_count <= N;
        else if (dec)
            i_count <= i_count - 5'd1;
    end

endmodule

Entrega Final/divisor/reg_Q.v
module reg_Q (
    input  wire        clk,
    input  wire        ldq,    
    input  wire        sh,     
    input  wire        q0,     
    input  wire [15:0] in_Q,   
    output reg  [15:0] Q
);

    always @(negedge clk) begin
        if (ldq)
            Q <= in_Q;
        else if (sh)
            Q <= {Q[14:0], q0};
        else if (q0)
            Q[0] <= 1'b1;
    end

endmodule

Entrega Final/divisor/reg_R.v
module reg_R (
    input  wire        clk,
    input  wire        reset_r,  
    input  wire        ldr,      
    input  wire        sh,       
    input  wire [15:0] in_R,     
    input  wire        msb_Q,    
    output reg  [15:0] R
);

    always @(negedge clk) begin
        if (reset_r)
            R <= 16'b0;
        else if (ldr)
            R <= in_R;
        else if (sh)
            R <= {R[14:0], msb_Q};
    end

endmodule

Entrega Final/divisor/divisor.v
module divisor (
    input  wire        clk,
    input  wire        rst,    // reset global del sistema
    input  wire        start,
    input  wire [15:0] Q,      // dividendo
    input  wire [15:0] V,      // divisor
    output wire [15:0] P,      // cociente
    output wire [15:0] R,      // residuo
    output wire         done
);

    wire w_LDR, w_Q0, w_SH, w_LDQ, w_DECi;

    wire w_msb_r, w_z;

    wire [15:0] w_Rreg, w_Qreg, w_diff;
    wire [4:0]  w_icount;

    //  DATAPATH 

    reg_R u_reg_R (
        .clk     (clk),
        .reset_r (w_LDQ),
        .ldr     (w_LDR),
        .sh      (w_SH),
        .in_R    (w_diff),
        .msb_Q   (w_Qreg[15]),
        .R       (w_Rreg)
    );

    reg_Q u_reg_Q (
        .clk  (clk),
        .ldq  (w_LDQ),
        .sh   (w_SH),
        .q0   (w_Q0),
        .in_Q (Q),
        .Q    (w_Qreg)
    );

    reg_i u_reg_i (
        .clk     (clk),
        .reset_i (w_LDQ),
        .dec     (w_DECi),
        .i_count (w_icount)
    );

    comp_i u_comp_i (
        .i_count (w_icount),
        .z       (w_z)
    );

    sumador_comp u_sum (
        .R     (w_Rreg),
        .V     (V),
        .diff  (w_diff),
        .MSB_R (w_msb_r)
    );

    // CONTROL 

    control_div u_ctrl (
        .clk   (clk),
        .rst   (rst),
        .start (start),
        .msb_r (w_msb_r),
        .z     (w_z),
        .done  (done),
        .LDR   (w_LDR),
        .Q0    (w_Q0),
        .SH    (w_SH),
        .LDQ   (w_LDQ),
        .DECi  (w_DECi)
    );

    // Salidas 
    assign P = w_Qreg;
    assign R = w_Rreg;

endmodule

Entrega Final/divisor/divisor_tb.v
`timescale 1ns/1ps

module divisor_tb;

    reg         clk;
    reg         rst;
    reg         start;
    reg  [15:0] Qin;
    reg  [15:0] Vin;
    wire [15:0] P;
    wire [15:0] R;
    wire        done;

    integer pruebas = 0;
    integer errores = 0;

    divisor uut (
        .clk   (clk),
        .rst   (rst),
        .start (start),
        .Q     (Qin),
        .V     (Vin),
        .P     (P),
        .R     (R),
        .done  (done)
    );

    initial clk = 1'b0;
    always #10 clk = ~clk;

    task ejecutar_prueba(input [15:0] valQ, input [15:0] valV);
        reg [15:0] esperadoP;
        reg [15:0] esperadoR;
        begin
            esperadoP = valQ / valV;
            esperadoR = valQ % valV;

            @(posedge clk); #2;
            Qin   = valQ;
            Vin   = valV;
            start = 1'b1;

            @(posedge clk); #2;
            start = 1'b0;

            wait (done == 1'b1);
            pruebas = pruebas + 1;

            if (P !== esperadoP || R !== esperadoR) begin
                errores = errores + 1;
                $display("[%0t] FALLO -> Q=%0d V=%0d : P=%0d R=%0d (se esperaba P=%0d R=%0d)",
                          $time, valQ, valV, P, R, esperadoP, esperadoR);
            end else begin
                $display("[%0t] OK    -> Q=%0d / V=%0d = P=%0d resto %0d",
                          $time, valQ, valV, P, R);
            end

            @(posedge clk); #2;
        end
    endtask

    initial begin
        $dumpfile("divisor_tb.vcd");
        $dumpvars(0, divisor_tb);

        rst   = 1'b1;
        start = 1'b0;
        Qin   = 16'd0;
        Vin   = 16'd0;

        #23;
        rst = 1'b0;

        ejecutar_prueba(16'd10,    16'd3);
        ejecutar_prueba(16'd0,     16'd5);
        ejecutar_prueba(16'd100,   16'd1);
        ejecutar_prueba(16'd7,     16'd7);
        ejecutar_prueba(16'd255,   16'd16);
        ejecutar_prueba(16'd1,     16'd2);
        ejecutar_prueba(16'd65535, 16'd3);

        #40;
        $display("--------------------------------------------------");
        if (errores == 0)
            $display("RESULTADO: TODAS LAS PRUEBAS PASARON (%0d/%0d)", pruebas, pruebas);
        else
            $display("RESULTADO: %0d de %0d PRUEBAS FALLARON", errores, pruebas);
        $display("--------------------------------------------------");

        $finish;
    end

    // ---- Watchdog de seguridad (evita simulacion colgada) ----
    initial begin
        #100000;
        $display("ERROR: TIMEOUT - la simulacion no termino a tiempo");
        $finish;
    end

endmodule

Entrega Final/divisor/divisor_tb.vcd
$date
	Thu Jul 16 04:01:07 2026
$end
$version
	Icarus Verilog
$end
$timescale
	1ps
$end
$scope module divisor_tb $end
$var wire 1 ! done $end
$var wire 16 " R [15:0] $end
$var wire 16 # P [15:0] $end
$var reg 16 $ Qin [15:0] $end
$var reg 16 % Vin [15:0] $end
$var reg 1 & clk $end
$var reg 1 ' rst $end
$var reg 1 ( start $end
$var integer 32 ) errores [31:0] $end
$var integer 32 * pruebas [31:0] $end
$scope module uut $end
$var wire 16 + P [15:0] $end
$var wire 16 , Q [15:0] $end
$var wire 16 - R [15:0] $end
$var wire 16 . V [15:0] $end
$var wire 1 & clk $end
$var wire 1 ' rst $end
$var wire 1 ( start $end
$var wire 1 / w_z $end
$var wire 1 0 w_msb_r $end
$var wire 5 1 w_icount [4:0] $end
$var wire 16 2 w_diff [15:0] $end
$var wire 1 3 w_SH $end
$var wire 16 4 w_Rreg [15:0] $end
$var wire 16 5 w_Qreg [15:0] $end
$var wire 1 6 w_Q0 $end
$var wire 1 7 w_LDR $end
$var wire 1 8 w_LDQ $end
$var wire 1 9 w_DECi $end
$var wire 1 ! done $end
$scope module u_comp_i $end
$var wire 1 / z $end
$var wire 5 : i_count [4:0] $end
$upscope $end
$scope module u_ctrl $end
$var wire 1 & clk $end
$var wire 1 ' rst $end
$var wire 1 ( start $end
$var wire 1 / z $end
$var wire 1 0 msb_r $end
$var parameter 3 ; ADD_ST $end
$var parameter 3 < CHECK_I_ST $end
$var parameter 3 = CHECK_R_ST $end
$var parameter 3 > DONE_ST $end
$var parameter 3 ? SHIFT_ST $end
$var parameter 3 @ START_ST $end
$var reg 1 9 DECi $end
$var reg 1 8 LDQ $end
$var reg 1 7 LDR $end
$var reg 1 6 Q0 $end
$var reg 1 3 SH $end
$var reg 1 ! done $end
$var reg 3 A next_state [2:0] $end
$var reg 3 B state [2:0] $end
$upscope $end
$scope module u_reg_Q $end
$var wire 1 & clk $end
$var wire 16 C in_Q [15:0] $end
$var wire 1 8 ldq $end
$var wire 1 6 q0 $end
$var wire 1 3 sh $end
$var reg 16 D Q [15:0] $end
$upscope $end
$scope module u_reg_R $end
$var wire 1 & clk $end
$var wire 1 7 ldr $end
$var wire 1 E msb_Q $end
$var wire 1 8 reset_r $end
$var wire 1 3 sh $end
$var wire 16 F in_R [15:0] $end
$var reg 16 G R [15:0] $end
$upscope $end
$scope module u_reg_i $end
$var wire 1 & clk $end
$var wire 1 9 dec $end
$var wire 1 8 reset_i $end
$var parameter 5 H N $end
$var reg 5 I i_count [4:0] $end
$upscope $end
$scope module u_sum $end
$var wire 1 0 MSB_R $end
$var wire 16 J R [15:0] $end
$var wire 16 K V [15:0] $end
$var wire 17 L resta [16:0] $end
$var wire 16 M diff [15:0] $end
$upscope $end
$upscope $end
$scope task ejecutar_prueba $end
$var reg 16 N esperadoP [15:0] $end
$var reg 16 O esperadoR [15:0] $end
$var reg 16 P valQ [15:0] $end
$var reg 16 Q valV [15:0] $end
$upscope $end
$upscope $end
$enddefinitions $end
$comment Show the parameter values. $end
$dumpall
b10000 H
b0 @
b10 ?
b101 >
b11 =
b1 <
b100 ;
$end
#0
$dumpvars
bx Q
bx P
bx O
bx N
bx M
bx L
b0 K
bx J
bx I
bx G
bx F
xE
bx D
b0 C
b0 B
b0 A
bx :
09
18
07
06
bx 5
bx 4
03
bx 2
bx 1
x0
x/
b0 .
bx -
b0 ,
bx +
b0 *
b0 )
0(
1'
0&
b0 %
b0 $
bx #
bx "
0!
$end
#10000
1&
#20000
10
0E
b0 2
b0 F
b0 M
0/
b10000 1
b10000 :
b10000 I
b0 #
b0 +
b0 5
b0 D
b0 L
b0 "
b0 -
b0 4
b0 G
b0 J
0&
#23000
b1 O
b11 N
b11 Q
b1010 P
0'
#30000
1&
#32000
00
b1 A
b1111111111111101 2
b1111111111111101 F
b1111111111111101 M
1(
b11111111111111101 L
b11 %
b11 .
b11 K
b1010 $
b1010 ,
b1010 C
#40000
b1010 #
b1010 +
b1010 5
b1010 D
0&
#50000
08
b10 A
b1 B
1&
#52000
0(
#60000
0&
#70000
19
13
b11 A
b10 B
1&
#80000
b10100 #
b10100 +
b10100 5
b10100 D
b1111 1
b1111 :
b1111 I
0&
#90000
09
03
b1 A
b11 B
1&
#100000
0&
#110000
b10 A
b1 B
1&
#120000
0&
#130000
19
13
b11 A
b10 B
1&
#140000
b1110 1
b1110 :
b1110 I
b101000 #
b101000 +
b101000 5
b101000 D
0&
#150000
09
03
b1 A
b11 B
1&
#160000
0&
#170000
b10 A
b1 B
1&
#180000
0&
#190000
19
13
b11 A
b10 B
1&
#200000
b1010000 #
b1010000 +
b1010000 5
b1010000 D
b1101 1
b1101 :
b1101 I
0&
#210000
09
03
b1 A
b11 B
1&
#220000
0&
#230000
b10 A
b1 B
1&
#240000
0&
#250000
19
13
b11 A
b10 B
1&
#260000
b1100 1
b1100 :
b1100 I
b10100000 #
b10100000 +
b10100000 5
b10100000 D
0&
#270000
09
03
b1 A
b11 B
1&
#280000
0&
#290000
b10 A
b1 B
1&
#300000
0&
#310000
19
13
b11 A
b10 B
1&
#320000
b101000000 #
b101000000 +
b101000000 5
b101000000 D
b1011 1
b1011 :
b1011 I
0&
#330000
09
03
b1 A
b11 B
1&
#340000
0&
#350000
b10 A
b1 B
1&
#360000
0&
#370000
19
13
b11 A
b10 B
1&
#380000
b1010 1
b1010 :
b1010 I
b1010000000 #
b1010000000 +
b1010000000 5
b1010000000 D
0&
#390000
09
03
b1 A
b11 B
1&
#400000
0&
#410000
b10 A
b1 B
1&
#420000
0&
#430000
19
13
b11 A
b10 B
1&
#440000
b10100000000 #
b10100000000 +
b10100000000 5
b10100000000 D
b1001 1
b1001 :
b1001 I
0&
#450000
09
03
b1 A
b11 B
1&
#460000
0&
#470000
b10 A
b1 B
1&
#480000
0&
#490000
19
13
b11 A
b10 B
1&
#500000
b1000 1
b1000 :
b1000 I
b101000000000 #
b101000000000 +
b101000000000 5
b101000000000 D
0&
#510000
09
03
b1 A
b11 B
1&
#520000
0&
#530000
b10 A
b1 B
1&
#540000
0&
#550000
19
13
b11 A
b10 B
1&
#560000
b1010000000000 #
b1010000000000 +
b1010000000000 5
b1010000000000 D
b111 1
b111 :
b111 I
0&
#570000
09
03
b1 A
b11 B
1&
#580000
0&
#590000
b10 A
b1 B
1&
#600000
0&
#610000
19
13
b11 A
b10 B
1&
#620000
b110 1
b110 :
b110 I
b10100000000000 #
b10100000000000 +
b10100000000000 5
b10100000000000 D
0&
#630000
09
03
b1 A
b11 B
1&
#640000
0&
#650000
b10 A
b1 B
1&
#660000
0&
#670000
19
13
b11 A
b10 B
1&
#680000
b101000000000000 #
b101000000000000 +
b101000000000000 5
b101000000000000 D
b101 1
b101 :
b101 I
0&
#690000
09
03
b1 A
b11 B
1&
#700000
0&
#710000
b10 A
b1 B
1&
#720000
0&
#730000
19
13
b11 A
b10 B
1&
#740000
1E
b100 1
b100 :
b100 I
b1010000000000000 #
b1010000000000000 +
b1010000000000000 5
b1010000000000000 D
0&
#750000
09
03
b1 A
b11 B
1&
#760000
0&
#770000
b10 A
b1 B
1&
#780000
0&
#790000
19
13
b11 A
b10 B
1&
#800000
b1111111111111110 2
b1111111111111110 F
b1111111111111110 M
0E
b11111111111111110 L
b1 "
b1 -
b1 4
b1 G
b1 J
b100000000000000 #
b100000000000000 +
b100000000000000 5
b100000000000000 D
b11 1
b11 :
b11 I
0&
#810000
09
03
b1 A
b11 B
1&
#820000
0&
#830000
b10 A
b1 B
1&
#840000
0&
#850000
19
13
b11 A
b10 B
1&
#860000
1E
b1111111111111111 2
b1111111111111111 F
b1111111111111111 M
b10 1
b10 :
b10 I
b1000000000000000 #
b1000000000000000 +
b1000000000000000 5
b1000000000000000 D
b11111111111111111 L
b10 "
b10 -
b10 4
b10 G
b10 J
0&
#870000
09
03
b1 A
b11 B
1&
#880000
0&
#890000
b10 A
b1 B
1&
#900000
0&
#910000
19
13
b11 A
b10 B
1&
#920000
10
b10 2
b10 F
b10 M
0E
b10 L
b101 "
b101 -
b101 4
b101 G
b101 J
b0 #
b0 +
b0 5
b0 D
b1 1
b1 :
b1 I
0&
#930000
09
03
b100 A
b11 B
1&
#940000
0&
#950000
16
17
b1 A
b100 B
1&
#960000
00
b1111111111111111 2
b1111111111111111 F
b1111111111111111 M
b11111111111111111 L
b10 "
b10 -
b10 4
b10 G
b10 J
b1 #
b1 +
b1 5
b1 D
0&
#970000
06
07
b10 A
b1 B
1&
#980000
0&
#990000
19
13
b11 A
b10 B
1&
#1000000
10
b1 2
b1 F
b1 M
b1 L
b100 "
b100 -
b100 4
b100 G
b100 J
b10 #
b10 +
b10 5
b10 D
1/
b0 1
b0 :
b0 I
0&
#1010000
09
03
b100 A
b11 B
1&
#1020000
0&
#1030000
16
17
b1 A
b100 B
1&
#1040000
00
b1111111111111110 2
b1111111111111110 F
b1111111111111110 M
b11111111111111110 L
b1 "
b1 -
b1 4
b1 G
b1 J
b11 #
b11 +
b11 5
b11 D
0&
#1050000
06
07
b101 A
b1 B
1&
#1060000
0&
#1070000
b1 *
1!
b0 A
b101 B
1&
#1080000
0&
#1090000
18
0!
b0 B
1&
#1092000
b0 O
b0 N
b101 Q
b0 P
#1100000
b1111111111111101 2
b1111111111111101 F
b1111111111111101 M
0/
b10000 1
b10000 :
b10000 I
b1010 #
b1010 +
b1010 5
b1010 D
b11111111111111101 L
b0 "
b0 -
b0 4
b0 G
b0 J
0&
#1110000
1&
#1112000
b1 A
b1111111111111011 2
b1111111111111011 F
b1111111111111011 M
1(
b11111111111111011 L
b101 %
b101 .
b101 K
b0 $
b0 ,
b0 C
#1120000
b0 #
b0 +
b0 5
b0 D
0&
#1130000
08
b10 A
b1 B
1&
#1132000
0(
#1140000
0&
#1150000
19
13
b11 A
b10 B
1&
#1160000
b1111 1
b1111 :
b1111 I
0&
#1170000
09
03
b1 A
b11 B
1&
#1180000
0&
#1190000
b10 A
b1 B
1&
#1200000
0&
#1210000
19
13
b11 A
b10 B
1&
#1220000
b1110 1
b1110 :
b1110 I
0&
#1230000
09
03
b1 A
b11 B
1&
#1240000
0&
#1250000
b10 A
b1 B
1&
#1260000
0&
#1270000
19
13
b11 A
b10 B
1&
#1280000
b1101 1
b1101 :
b1101 I
0&
#1290000
09
03
b1 A
b11 B
1&
#1300000
0&
#1310000
b10 A
b1 B
1&
#1320000
0&
#1330000
19
13
b11 A
b10 B
1&
#1340000
b1100 1
b1100 :
b1100 I
0&
#1350000
09
03
b1 A
b11 B
1&
#1360000
0&
#1370000
b10 A
b1 B
1&
#1380000
0&
#1390000
19
13
b11 A
b10 B
1&
#1400000
b1011 1
b1011 :
b1011 I
0&
#1410000
09
03
b1 A
b11 B
1&
#1420000
0&
#1430000
b10 A
b1 B
1&
#1440000
0&
#1450000
19
13
b11 A
b10 B
1&
#1460000
b1010 1
b1010 :
b1010 I
0&
#1470000
09
03
b1 A
b11 B
1&
#1480000
0&
#1490000
b10 A
b1 B
1&
#1500000
0&
#1510000
19
13
b11 A
b10 B
1&
#1520000
b1001 1
b1001 :
b1001 I
0&
#1530000
09
03
b1 A
b11 B
1&
#1540000
0&
#1550000
b10 A
b1 B
1&
#1560000
0&
#1570000
19
13
b11 A
b10 B
1&
#1580000
b1000 1
b1000 :
b1000 I
0&
#1590000
09
03
b1 A
b11 B
1&
#1600000
0&
#1610000
b10 A
b1 B
1&
#1620000
0&
#1630000
19
13
b11 A
b10 B
1&
#1640000
b111 1
b111 :
b111 I
0&
#1650000
09
03
b1 A
b11 B
1&
#1660000
0&
#1670000
b10 A
b1 B
1&
#1680000
0&
#1690000
19
13
b11 A
b10 B
1&
#1700000
b110 1
b110 :
b110 I
0&
#1710000
09
03
b1 A
b11 B
1&
#1720000
0&
#1730000
b10 A
b1 B
1&
#1740000
0&
#1750000
19
13
b11 A
b10 B
1&
#1760000
b101 1
b101 :
b101 I
0&
#1770000
09
03
b1 A
b11 B
1&
#1780000
0&
#1790000
b10 A
b1 B
1&
#1800000
0&
#1810000
19
13
b11 A
b10 B
1&
#1820000
b100 1
b100 :
b100 I
0&
#1830000
09
03
b1 A
b11 B
1&
#1840000
0&
#1850000
b10 A
b1 B
1&
#1860000
0&
#1870000
19
13
b11 A
b10 B
1&
#1880000
b11 1
b11 :
b11 I
0&
#1890000
09
03
b1 A
b11 B
1&
#1900000
0&
#1910000
b10 A
b1 B
1&
#1920000
0&
#1930000
19
13
b11 A
b10 B
1&
#1940000
b10 1
b10 :
b10 I
0&
#1950000
09
03
b1 A
b11 B
1&
#1960000
0&
#1970000
b10 A
b1 B
1&
#1980000
0&
#1990000
19
13
b11 A
b10 B
1&
#2000000
b1 1
b1 :
b1 I
0&
#2010000
09
03
b1 A
b11 B
1&
#2020000
0&
#2030000
b10 A
b1 B
1&
#2040000
0&
#2050000
19
13
b11 A
b10 B
1&
#2060000
1/
b0 1
b0 :
b0 I
0&
#2070000
09
03
b1 A
b11 B
1&
#2080000
0&
#2090000
b101 A
b1 B
1&
#2100000
0&
#2110000
b10 *
1!
b0 A
b101 B
1&
#2120000
0&
#2130000
18
0!
b0 B
1&
#2132000
b1100100 N
b1 Q
b1100100 P
#2140000
0/
b10000 1
b10000 :
b10000 I
0&
#2150000
1&
#2152000
b1 A
b1111111111111111 2
b1111111111111111 F
b1111111111111111 M
1(
b11111111111111111 L
b1 %
b1 .
b1 K
b1100100 $
b1100100 ,
b1100100 C
#2160000
b1100100 #
b1100100 +
b1100100 5
b1100100 D
0&
#2170000
08
b10 A
b1 B
1&
#2172000
0(
#2180000
0&
#2190000
19
13
b11 A
b10 B
1&
#2200000
b11001000 #
b11001000 +
b11001000 5
b11001000 D
b1111 1
b1111 :
b1111 I
0&
#2210000
09
03
b1 A
b11 B
1&
#2220000
0&
#2230000
b10 A
b1 B
1&
#2240000
0&
#2250000
19
13
b11 A
b10 B
1&
#2260000
b1110 1
b1110 :
b1110 I
b110010000 #
b110010000 +
b110010000 5
b110010000 D
0&
#2270000
09
03
b1 A
b11 B
1&
#2280000
0&
#2290000
b10 A
b1 B
1&
#2300000
0&
#2310000
19
13
b11 A
b10 B
1&
#2320000
b1100100000 #
b1100100000 +
b1100100000 5
b1100100000 D
b1101 1
b1101 :
b1101 I
0&
#2330000
09
03
b1 A
b11 B
1&
#2340000
0&
#2350000
b10 A
b1 B
1&
#2360000
0&
#2370000
19
13
b11 A
b10 B
1&
#2380000
b1100 1
b1100 :
b1100 I
b11001000000 #
b11001000000 +
b11001000000 5
b11001000000 D
0&
#2390000
09
03
b1 A
b11 B
1&
#2400000
0&
#2410000
b10 A
b1 B
1&
#2420000
0&
#2430000
19
13
b11 A
b10 B
1&
#2440000
b110010000000 #
b110010000000 +
b110010000000 5
b110010000000 D
b1011 1
b1011 :
b1011 I
0&
#2450000
09
03
b1 A
b11 B
1&
#2460000
0&
#2470000
b10 A
b1 B
1&
#2480000
0&
#2490000
19
13
b11 A
b10 B
1&
#2500000
b1010 1
b1010 :
b1010 I
b1100100000000 #
b1100100000000 +
b1100100000000 5
b1100100000000 D
0&
#2510000
09
03
b1 A
b11 B
1&
#2520000
0&
#2530000
b10 A
b1 B
1&
#2540000
0&
#2550000
19
13
b11 A
b10 B
1&
#2560000
b11001000000000 #
b11001000000000 +
b11001000000000 5
b11001000000000 D
b1001 1
b1001 :
b1001 I
0&
#2570000
09
03
b1 A
b11 B
1&
#2580000
0&
#2590000
b10 A
b1 B
1&
#2600000
0&
#2610000
19
13
b11 A
b10 B
1&
#2620000
b1000 1
b1000 :
b1000 I
b110010000000000 #
b110010000000000 +
b110010000000000 5
b110010000000000 D
0&
#2630000
09
03
b1 A
b11 B
1&
#2640000
0&
#2650000
b10 A
b1 B
1&
#2660000
0&
#2670000
19
13
b11 A
b10 B
1&
#2680000
1E
b1100100000000000 #
b1100100000000000 +
b1100100000000000 5
b1100100000000000 D
b111 1
b111 :
b111 I
0&
#2690000
09
03
b1 A
b11 B
1&
#2700000
0&
#2710000
b10 A
b1 B
1&
#2720000
0&
#2730000
19
13
b11 A
b10 B
1&
#2740000
10
b0 2
b0 F
b0 M
b110 1
b110 :
b110 I
b1001000000000000 #
b1001000000000000 +
b1001000000000000 5
b1001000000000000 D
b0 L
b1 "
b1 -
b1 4
b1 G
b1 J
0&
#2750000
09
03
b100 A
b11 B
1&
#2760000
0&
#2770000
16
17
b1 A
b100 B
1&
#2780000
00
b1111111111111111 2
b1111111111111111 F
b1111111111111111 M
b1001000000000001 #
b1001000000000001 +
b1001000000000001 5
b1001000000000001 D
b11111111111111111 L
b0 "
b0 -
b0 4
b0 G
b0 J
0&
#2790000
06
07
b10 A
b1 B
1&
#2800000
0&
#2810000
19
13
b11 A
b10 B
1&
#2820000
10
0E
b0 2
b0 F
b0 M
b101 1
b101 :
b101 I
b10000000000010 #
b10000000000010 +
b10000000000010 5
b10000000000010 D
b0 L
b1 "
b1 -
b1 4
b1 G
b1 J
0&
#2830000
09
03
b100 A
b11 B
1&
#2840000
0&
#2850000
16
17
b1 A
b100 B
1&
#2860000
00
b1111111111111111 2
b1111111111111111 F
b1111111111111111 M
b10000000000011 #
b10000000000011 +
b10000000000011 5
b10000000000011 D
b11111111111111111 L
b0 "
b0 -
b0 4
b0 G
b0 J
0&
#2870000
06
07
b10 A
b1 B
1&
#2880000
0&
#2890000
19
13
b11 A
b10 B
1&
#2900000
b100 1
b100 :
b100 I
b100000000000110 #
b100000000000110 +
b100000000000110 5
b100000000000110 D
0&
#2910000
09
03
b1 A
b11 B
1&
#2920000
0&
#2930000
b10 A
b1 B
1&
#2940000
0&
#2950000
19
13
b11 A
b10 B
1&
#2960000
1E
b1000000000001100 #
b1000000000001100 +
b1000000000001100 5
b1000000000001100 D
b11 1
b11 :
b11 I
0&
#2970000
09
03
b1 A
b11 B
1&
#2980000
0&
#2990000
b10 A
b1 B
1&
#3000000
0&
#3010000
19
13
b11 A
b10 B
1&
#3020000
10
0E
b0 2
b0 F
b0 M
b10 1
b10 :
b10 I
b11000 #
b11000 +
b11000 5
b11000 D
b0 L
b1 "
b1 -
b1 4
b1 G
b1 J
0&
#3030000
09
03
b100 A
b11 B
1&
#3040000
0&
#3050000
16
17
b1 A
b100 B
1&
#3060000
00
b1111111111111111 2
b1111111111111111 F
b1111111111111111 M
b11001 #
b11001 +
b11001 5
b11001 D
b11111111111111111 L
b0 "
b0 -
b0 4
b0 G
b0 J
0&
#3070000
06
07
b10 A
b1 B
1&
#3080000
0&
#3090000
19
13
b11 A
b10 B
1&
#3100000
b1 1
b1 :
b1 I
b110010 #
b110010 +
b110010 5
b110010 D
0&
#3110000
09
03
b1 A
b11 B
1&
#3120000
0&
#3130000
b10 A
b1 B
1&
#3140000
0&
#3150000
19
13
b11 A
b10 B
1&
#3160000
b1100100 #
b1100100 +
b1100100 5
b1100100 D
1/
b0 1
b0 :
b0 I
0&
#3170000
09
03
b1 A
b11 B
1&
#3180000
0&
#3190000
b101 A
b1 B
1&
#3200000
0&
#3210000
b11 *
1!
b0 A
b101 B
1&
#3220000
0&
#3230000
18
0!
b0 B
1&
#3232000
b1 N
b111 Q
b111 P
#3240000
0/
b10000 1
b10000 :
b10000 I
0&
#3250000
1&
#3252000
b1 A
b1111111111111001 2
b1111111111111001 F
b1111111111111001 M
1(
b11111111111111001 L
b111 %
b111 .
b111 K
b111 $
b111 ,
b111 C
#3260000
b111 #
b111 +
b111 5
b111 D
0&
#3270000
08
b10 A
b1 B
1&
#3272000
0(
#3280000
0&
#3290000
19
13
b11 A
b10 B
1&
#3300000
b1111 1
b1111 :
b1111 I
b1110 #
b1110 +
b1110 5
b1110 D
0&
#3310000
09
03
b1 A
b11 B
1&
#3320000
0&
#3330000
b10 A
b1 B
1&
#3340000
0&
#3350000
19
13
b11 A
b10 B
1&
#3360000
b11100 #
b11100 +
b11100 5
b11100 D
b1110 1
b1110 :
b1110 I
0&
#3370000
09
03
b1 A
b11 B
1&
#3380000
0&
#3390000
b10 A
b1 B
1&
#3400000
0&
#3410000
19
13
b11 A
b10 B
1&
#3420000
b1101 1
b1101 :
b1101 I
b111000 #
b111000 +
b111000 5
b111000 D
0&
#3430000
09
03
b1 A
b11 B
1&
#3440000
0&
#3450000
b10 A
b1 B
1&
#3460000
0&
#3470000
19
13
b11 A
b10 B
1&
#3480000
b1110000 #
b1110000 +
b1110000 5
b1110000 D
b1100 1
b1100 :
b1100 I
0&
#3490000
09
03
b1 A
b11 B
1&
#3500000
0&
#3510000
b10 A
b1 B
1&
#3520000
0&
#3530000
19
13
b11 A
b10 B
1&
#3540000
b1011 1
b1011 :
b1011 I
b11100000 #
b11100000 +
b11100000 5
b11100000 D
0&
#3550000
09
03
b1 A
b11 B
1&
#3560000
0&
#3570000
b10 A
b1 B
1&
#3580000
0&
#3590000
19
13
b11 A
b10 B
1&
#3600000
b111000000 #
b111000000 +
b111000000 5
b111000000 D
b1010 1
b1010 :
b1010 I
0&
#3610000
09
03
b1 A
b11 B
1&
#3620000
0&
#3630000
b10 A
b1 B
1&
#3640000
0&
#3650000
19
13
b11 A
b10 B
1&
#3660000
b1001 1
b1001 :
b1001 I
b1110000000 #
b1110000000 +
b1110000000 5
b1110000000 D
0&
#3670000
09
03
b1 A
b11 B
1&
#3680000
0&
#3690000
b10 A
b1 B
1&
#3700000
0&
#3710000
19
13
b11 A
b10 B
1&
#3720000
b11100000000 #
b11100000000 +
b11100000000 5
b11100000000 D
b1000 1
b1000 :
b1000 I
0&
#3730000
09
03
b1 A
b11 B
1&
#3740000
0&
#3750000
b10 A
b1 B
1&
#3760000
0&
#3770000
19
13
b11 A
b10 B
1&
#3780000
b111 1
b111 :
b111 I
b111000000000 #
b111000000000 +
b111000000000 5
b111000000000 D
0&
#3790000
09
03
b1 A
b11 B
1&
#3800000
0&
#3810000
b10 A
b1 B
1&
#3820000
0&
#3830000
19
13
b11 A
b10 B
1&
#3840000
b1110000000000 #
b1110000000000 +
b1110000000000 5
b1110000000000 D
b110 1
b110 :
b110 I
0&
#3850000
09
03
b1 A
b11 B
1&
#3860000
0&
#3870000
b10 A
b1 B
1&
#3880000
0&
#3890000
19
13
b11 A
b10 B
1&
#3900000
b101 1
b101 :
b101 I
b11100000000000 #
b11100000000000 +
b11100000000000 5
b11100000000000 D
0&
#3910000
09
03
b1 A
b11 B
1&
#3920000
0&
#3930000
b10 A
b1 B
1&
#3940000
0&
#3950000
19
13
b11 A
b10 B
1&
#3960000
b111000000000000 #
b111000000000000 +
b111000000000000 5
b111000000000000 D
b100 1
b100 :
b100 I
0&
#3970000
09
03
b1 A
b11 B
1&
#3980000
0&
