Entrega Final/contador_unos/control_unos.v
module control_unos (
    input  wire clk,
    input  wire rst,    
    input  wire start,
    input  wire lsb_a,  
    input  wire z,      

    output reg  done,
    output reg  SH,
    output reg  LD,
    output reg  INC
);

    localparam [2:0] START_ST      = 3'b000;
    localparam [2:0] CHECK_A_ST    = 3'b001;
    localparam [2:0] CHECK_LSB_ST  = 3'b010;
    localparam [2:0] SHIFT_ST      = 3'b011;
    localparam [2:0] INCREMENTO_ST = 3'b100;
    localparam [2:0] DONE_ST       = 3'b101;

    reg [2:0] state, next_state;

    always @(posedge clk or posedge rst) begin
        if (rst)
            state <= START_ST;
        else
            state <= next_state;
    end

    always @(*) begin
        case (state)
            START_ST:      next_state = start  ? CHECK_A_ST    : START_ST;
            CHECK_A_ST:    next_state = z      ? DONE_ST        : CHECK_LSB_ST;
            CHECK_LSB_ST:  next_state = lsb_a  ? INCREMENTO_ST  : SHIFT_ST;
            INCREMENTO_ST: next_state = SHIFT_ST;
            SHIFT_ST:      next_state = CHECK_A_ST;
            DONE_ST:       next_state = START_ST;
            default:       next_state = START_ST;
        endcase
    end

    always @(*) begin
        done = 1'b0;
        SH   = 1'b0;
        LD   = 1'b0;
        INC  = 1'b0;
        case (state)
            START_ST: begin
                LD = 1'b1;
            end
            CHECK_A_ST:   ; // solo decide
            CHECK_LSB_ST: ; // solo decide
            SHIFT_ST: begin
                SH = 1'b1;
            end
            INCREMENTO_ST: begin
                INC = 1'b1;
            end
            DONE_ST: begin
                done = 1'b1;
            end
            default: ;
        endcase
    end

endmodule

Entrega Final/contador_unos/reg_C.v
module reg_C (
    input  wire       clk,
    input  wire       ld,   
    input  wire       inc,  
    output reg  [4:0] C
);

    always @(negedge clk) begin
        if (ld)
            C <= 5'b0;
        else if (inc)
            C <= C + 5'd1;
    end

endmodule

Entrega Final/contador_unos/comp.v
module comp_unos (
    input  wire [15:0] A,
    output wire         z
);

    assign z = (A == 16'b0);

endmodule

Entrega Final/contador_unos/reg_A.v
module reg_A_unos (
    input  wire        clk,
    input  wire        sh,     
    input  wire        ld,     
    input  wire [15:0] in_A,
    output reg  [15:0] A,
    output wire         LSB_A
);

    always @(negedge clk) begin
        if (ld)
            A <= in_A;
        else if (sh)
            A <= A >> 1;
    end

    assign LSB_A = A[0];

endmodule

Entrega Final/contador_unos/contador_unos.v
module contador_unos (
    input  wire        clk,
    input  wire        rst,    // reset global del sistema
    input  wire        start,
    input  wire [15:0] A,
    output wire [4:0]  C,
    output wire         done
);

    //  Senales de control 
    wire w_SH, w_LD, w_INC;

    // ---- Senales de estado (Datapath -> Control) ----
    wire w_lsb_a, w_z;

    // ---- Buses internos del datapath ----
    wire [15:0] w_Areg;
    wire [4:0]  w_Creg;

    // DATAPATH 

    reg_A_unos u_reg_A (
        .clk   (clk),
        .sh    (w_SH),
        .ld    (w_LD),
        .in_A  (A),
        .A     (w_Areg),
        .LSB_A (w_lsb_a)
    );

    comp_unos u_comp (
        .A (w_Areg),
        .z (w_z)
    );

    reg_C u_reg_C (
        .clk (clk),
        .ld  (w_LD),
        .inc (w_INC),
        .C   (w_Creg)
    );

    // CONTROL 

    control_unos u_ctrl (
        .clk   (clk),
        .rst   (rst),
        .start (start),
        .lsb_a (w_lsb_a),
        .z     (w_z),
        .done  (done),
        .SH    (w_SH),
        .LD    (w_LD),
        .INC   (w_INC)
    );

    assign C = w_Creg;

endmodule

Entrega Final/contador_unos/contador_unos_tb.v
`timescale 1ns/1ps

module contador_unos_tb;

    reg         clk;
    reg         rst;
    reg         start;
    reg  [15:0] Ain;
    wire [4:0]  C;
    wire        done;

    integer pruebas = 0;
    integer errores = 0;

    contador_unos uut (
        .clk   (clk),
        .rst   (rst),
        .start (start),
        .A     (Ain),
        .C     (C),
        .done  (done)
    );

    initial clk = 1'b0;
    always #10 clk = ~clk;

    function [4:0] contar_unos;
        input [15:0] val;
        integer j;
        begin
            contar_unos = 5'd0;
            for (j = 0; j < 16; j = j + 1)
                if (val[j])
                    contar_unos = contar_unos + 5'd1;
        end
    endfunction

    task ejecutar_prueba(input [15:0] valA);
        reg [4:0] esperado;
        begin
            esperado = contar_unos(valA);

            @(posedge clk); #2;
            Ain   = valA;
            start = 1'b1;

            @(posedge clk); #2;
            start = 1'b0;

            wait (done == 1'b1);
            pruebas = pruebas + 1;

            if (C !== esperado) begin
                errores = errores + 1;
                $display("[%0t] FALLO -> A=%b : C=%0d (se esperaba %0d)",
                          $time, valA, C, esperado);
            end else begin
                $display("[%0t] OK    -> A=%b tiene %0d unos",
                          $time, valA, C);
            end

            @(posedge clk); #2;
        end
    endtask

    initial begin
        $dumpfile("contador_unos_tb.vcd");
        $dumpvars(0, contador_unos_tb);

        rst   = 1'b1;
        start = 1'b0;
        Ain   = 16'd0;

        #23;
        rst = 1'b0;

        ejecutar_prueba(16'h0000);
        ejecutar_prueba(16'hFFFF);
        ejecutar_prueba(16'h0001);
        ejecutar_prueba(16'h8000);
        ejecutar_prueba(16'hAAAA);
        ejecutar_prueba(16'h00FF);
        ejecutar_prueba(16'h1234);

        #40;
        $display("--------------------------------------------------");
        if (errores == 0)
            $display("RESULTADO: TODAS LAS PRUEBAS PASARON (%0d/%0d)", pruebas, pruebas);
        else
            $display("RESULTADO: %0d de %0d PRUEBAS FALLARON", errores, pruebas);
        $display("--------------------------------------------------");

        $finish;
    end

    initial begin
        #100000;
        $display("ERROR: TIMEOUT - la simulacion no termino a tiempo");
        $finish;
    end

endmodule

Entrega Final/contador_unos/contador_unos_tb.vcd
$date
	Thu Jul 16 04:00:57 2026
$end
$version
	Icarus Verilog
$end
$timescale
	1ps
$end
$scope module contador_unos_tb $end
$var wire 1 ! done $end
$var wire 5 " C [4:0] $end
$var reg 16 # Ain [15:0] $end
$var reg 1 $ clk $end
$var reg 1 % rst $end
$var reg 1 & start $end
$var integer 32 ' errores [31:0] $end
$var integer 32 ( pruebas [31:0] $end
$scope function contar_unos $end
$var reg 16 ) val [15:0] $end
$var integer 32 * j [31:0] $end
$upscope $end
$scope module uut $end
$var wire 16 + A [15:0] $end
$var wire 5 , C [4:0] $end
$var wire 1 $ clk $end
$var wire 1 % rst $end
$var wire 1 & start $end
$var wire 1 - w_z $end
$var wire 1 . w_lsb_a $end
$var wire 1 / w_SH $end
$var wire 1 0 w_LD $end
$var wire 1 1 w_INC $end
$var wire 5 2 w_Creg [4:0] $end
$var wire 16 3 w_Areg [15:0] $end
$var wire 1 ! done $end
$scope module u_comp $end
$var wire 1 - z $end
$var wire 16 4 A [15:0] $end
$upscope $end
$scope module u_ctrl $end
$var wire 1 $ clk $end
$var wire 1 % rst $end
$var wire 1 & start $end
$var wire 1 - z $end
$var wire 1 . lsb_a $end
$var parameter 3 5 CHECK_A_ST $end
$var parameter 3 6 CHECK_LSB_ST $end
$var parameter 3 7 DONE_ST $end
$var parameter 3 8 INCREMENTO_ST $end
$var parameter 3 9 SHIFT_ST $end
$var parameter 3 : START_ST $end
$var reg 1 1 INC $end
$var reg 1 0 LD $end
$var reg 1 / SH $end
$var reg 1 ! done $end
$var reg 3 ; next_state [2:0] $end
$var reg 3 < state [2:0] $end
$upscope $end
$scope module u_reg_A $end
$var wire 1 $ clk $end
$var wire 16 = in_A [15:0] $end
$var wire 1 0 ld $end
$var wire 1 / sh $end
$var wire 1 . LSB_A $end
$var reg 16 > A [15:0] $end
$upscope $end
$scope module u_reg_C $end
$var wire 1 $ clk $end
$var wire 1 1 inc $end
$var wire 1 0 ld $end
$var reg 5 ? C [4:0] $end
$upscope $end
$upscope $end
$scope task ejecutar_prueba $end
$var reg 5 @ esperado [4:0] $end
$var reg 16 A valA [15:0] $end
$upscope $end
$upscope $end
$enddefinitions $end
$comment Show the parameter values. $end
$dumpall
b0 :
b11 9
b100 8
b101 7
b10 6
b1 5
$end
#0
$dumpvars
bx A
bx @
bx ?
bx >
b0 =
b0 <
b0 ;
bx 4
bx 3
bx 2
01
10
0/
x.
x-
bx ,
b0 +
bx *
bx )
b0 (
b0 '
0&
1%
0$
b0 #
bx "
0!
$end
#10000
1$
#20000
0.
b0 "
b0 ,
b0 2
b0 ?
1-
b0 3
b0 4
b0 >
0$
#23000
b0 @
b10000 *
b0 )
b0 A
0%
#30000
1$
#32000
b1 ;
1&
#40000
0$
#50000
00
b101 ;
b1 <
1$
#52000
0&
#60000
0$
#70000
b1 (
1!
b0 ;
b101 <
1$
#80000
0$
#90000
10
0!
b0 <
1$
#92000
b10000 @
b10000 *
b1111111111111111 )
b1111111111111111 A
#100000
0$
#110000
1$
#112000
b1 ;
1&
b1111111111111111 #
b1111111111111111 +
b1111111111111111 =
#120000
1.
0-
b1111111111111111 3
b1111111111111111 4
b1111111111111111 >
0$
#130000
00
b10 ;
b1 <
1$
#132000
0&
#140000
0$
#150000
b100 ;
b10 <
1$
#160000
0$
#170000
11
b11 ;
b100 <
1$
#180000
b1 "
b1 ,
b1 2
b1 ?
0$
#190000
1/
01
b1 ;
b11 <
1$
#200000
b111111111111111 3
b111111111111111 4
b111111111111111 >
0$
#210000
0/
b10 ;
b1 <
1$
#220000
0$
#230000
b100 ;
b10 <
1$
#240000
0$
#250000
11
b11 ;
b100 <
1$
#260000
b10 "
b10 ,
b10 2
b10 ?
0$
#270000
1/
01
b1 ;
b11 <
1$
#280000
b11111111111111 3
b11111111111111 4
b11111111111111 >
0$
#290000
0/
b10 ;
b1 <
1$
#300000
0$
#310000
b100 ;
b10 <
1$
#320000
0$
#330000
11
b11 ;
b100 <
1$
#340000
b11 "
b11 ,
b11 2
b11 ?
0$
#350000
1/
01
b1 ;
b11 <
1$
#360000
b1111111111111 3
b1111111111111 4
b1111111111111 >
0$
#370000
0/
b10 ;
b1 <
1$
#380000
0$
#390000
b100 ;
b10 <
1$
#400000
0$
#410000
11
b11 ;
b100 <
1$
#420000
b100 "
b100 ,
b100 2
b100 ?
0$
#430000
1/
01
b1 ;
b11 <
1$
#440000
b111111111111 3
b111111111111 4
b111111111111 >
0$
#450000
0/
b10 ;
b1 <
1$
#460000
0$
#470000
b100 ;
b10 <
1$
#480000
0$
#490000
11
b11 ;
b100 <
1$
#500000
b101 "
b101 ,
b101 2
b101 ?
0$
#510000
1/
01
b1 ;
b11 <
1$
#520000
b11111111111 3
b11111111111 4
b11111111111 >
0$
#530000
0/
b10 ;
b1 <
1$
#540000
0$
#550000
b100 ;
b10 <
1$
#560000
0$
#570000
11
b11 ;
b100 <
1$
#580000
b110 "
b110 ,
b110 2
b110 ?
0$
#590000
1/
01
b1 ;
b11 <
1$
#600000
b1111111111 3
b1111111111 4
b1111111111 >
0$
#610000
0/
b10 ;
b1 <
1$
#620000
0$
#630000
b100 ;
b10 <
1$
#640000
0$
#650000
11
b11 ;
b100 <
1$
#660000
b111 "
b111 ,
b111 2
b111 ?
0$
#670000
1/
01
b1 ;
b11 <
1$
#680000
b111111111 3
b111111111 4
b111111111 >
0$
#690000
0/
b10 ;
b1 <
1$
#700000
0$
#710000
b100 ;
b10 <
1$
#720000
0$
#730000
11
b11 ;
b100 <
1$
#740000
b1000 "
b1000 ,
b1000 2
b1000 ?
0$
#750000
1/
01
b1 ;
b11 <
1$
#760000
b11111111 3
b11111111 4
b11111111 >
0$
#770000
0/
b10 ;
b1 <
1$
#780000
0$
#790000
b100 ;
b10 <
1$
#800000
0$
#810000
11
b11 ;
b100 <
1$
#820000
b1001 "
b1001 ,
b1001 2
b1001 ?
0$
#830000
1/
01
b1 ;
b11 <
1$
#840000
b1111111 3
b1111111 4
b1111111 >
0$
#850000
0/
b10 ;
b1 <
1$
#860000
0$
#870000
b100 ;
b10 <
1$
#880000
0$
#890000
11
b11 ;
b100 <
1$
#900000
b1010 "
b1010 ,
b1010 2
b1010 ?
0$
#910000
1/
01
b1 ;
b11 <
1$
#920000
b111111 3
b111111 4
b111111 >
0$
#930000
0/
b10 ;
b1 <
1$
#940000
0$
#950000
b100 ;
b10 <
1$
#960000
0$
#970000
11
b11 ;
b100 <
1$
#980000
b1011 "
b1011 ,
b1011 2
b1011 ?
0$
#990000
1/
01
b1 ;
b11 <
1$
#1000000
b11111 3
b11111 4
b11111 >
0$
#1010000
0/
b10 ;
b1 <
1$
#1020000
0$
#1030000
b100 ;
b10 <
1$
#1040000
0$
#1050000
11
b11 ;
b100 <
1$
#1060000
b1100 "
b1100 ,
b1100 2
b1100 ?
0$
#1070000
1/
01
b1 ;
b11 <
1$
#1080000
b1111 3
b1111 4
b1111 >
0$
#1090000
0/
b10 ;
b1 <
1$
#1100000
0$
#1110000
b100 ;
b10 <
1$
#1120000
0$
#1130000
11
b11 ;
b100 <
1$
#1140000
b1101 "
b1101 ,
b1101 2
b1101 ?
0$
#1150000
1/
01
b1 ;
b11 <
1$
#1160000
b111 3
b111 4
b111 >
0$
#1170000
0/
b10 ;
b1 <
1$
#1180000
0$
#1190000
b100 ;
b10 <
1$
#1200000
0$
#1210000
11
b11 ;
b100 <
1$
#1220000
b1110 "
b1110 ,
b1110 2
b1110 ?
0$
#1230000
1/
01
b1 ;
b11 <
1$
#1240000
b11 3
b11 4
b11 >
0$
#1250000
0/
b10 ;
b1 <
1$
#1260000
0$
#1270000
b100 ;
b10 <
1$
#1280000
0$
#1290000
11
b11 ;
b100 <
1$
#1300000
b1111 "
b1111 ,
b1111 2
b1111 ?
0$
#1310000
1/
01
b1 ;
b11 <
1$
#1320000
b1 3
b1 4
b1 >
0$
#1330000
0/
b10 ;
b1 <
1$
#1340000
0$
#1350000
b100 ;
b10 <
1$
#1360000
0$
#1370000
11
b11 ;
b100 <
1$
#1380000
b10000 "
b10000 ,
b10000 2
b10000 ?
0$
#1390000
1/
01
b1 ;
b11 <
1$
#1400000
0.
1-
b0 3
b0 4
b0 >
0$
#1410000
0/
b101 ;
b1 <
1$
#1420000
0$
#1430000
b10 (
1!
b0 ;
b101 <
1$
#1440000
0$
#1450000
10
0!
b0 <
1$
#1452000
b1 @
b10000 *
b1 )
b1 A
#1460000
1.
b0 "
b0 ,
b0 2
b0 ?
0-
b1111111111111111 3
b1111111111111111 4
b1111111111111111 >
0$
#1470000
1$
#1472000
b1 ;
1&
b1 #
b1 +
b1 =
#1480000
b1 3
b1 4
b1 >
0$
#1490000
00
b10 ;
b1 <
1$
#1492000
0&
#1500000
0$
#1510000
b100 ;
b10 <
1$
#1520000
0$
#1530000
11
b11 ;
b100 <
1$
#1540000
b1 "
b1 ,
b1 2
b1 ?
0$
#1550000
1/
01
b1 ;
b11 <
1$
#1560000
0.
1-
b0 3
b0 4
b0 >
0$
#1570000
0/
b101 ;
b1 <
1$
#1580000
0$
#1590000
b11 (
1!
b0 ;
b101 <
1$
#1600000
0$
#1610000
10
0!
b0 <
1$
#1612000
b10000 *
b1000000000000000 )
b1000000000000000 A
#1620000
1.
b0 "
b0 ,
b0 2
b0 ?
0-
b1 3
b1 4
b1 >
0$
#1630000
1$
#1632000
b1 ;
1&
b1000000000000000 #
b1000000000000000 +
b1000000000000000 =
#1640000
0.
b1000000000000000 3
b1000000000000000 4
b1000000000000000 >
0$
#1650000
00
b10 ;
b1 <
1$
#1652000
0&
#1660000
0$
#1670000
b11 ;
b10 <
1$
#1680000
0$
#1690000
1/
b1 ;
b11 <
1$
#1700000
b100000000000000 3
b100000000000000 4
b100000000000000 >
0$
#1710000
0/
b10 ;
b1 <
1$
#1720000
0$
#1730000
b11 ;
b10 <
1$
#1740000
0$
#1750000
1/
b1 ;
b11 <
1$
#1760000
b10000000000000 3
b10000000000000 4
b10000000000000 >
0$
#1770000
0/
b10 ;
b1 <
1$
#1780000
0$
#1790000
b11 ;
b10 <
1$
#1800000
0$
#1810000
1/
b1 ;
b11 <
1$
#1820000
b1000000000000 3
b1000000000000 4
b1000000000000 >
0$
#1830000
0/
b10 ;
b1 <
1$
#1840000
0$
#1850000
b11 ;
b10 <
1$
#1860000
0$
#1870000
1/
b1 ;
b11 <
1$
#1880000
b100000000000 3
b100000000000 4
b100000000000 >
0$
#1890000
0/
b10 ;
b1 <
1$
#1900000
0$
#1910000
b11 ;
b10 <
1$
#1920000
0$
#1930000
1/
b1 ;
b11 <
1$
#1940000
b10000000000 3
b10000000000 4
b10000000000 >
0$
#1950000
0/
b10 ;
b1 <
1$
#1960000
0$
#1970000
b11 ;
b10 <
1$
#1980000
0$
#1990000
1/
b1 ;
b11 <
1$
#2000000
b1000000000 3
b1000000000 4
b1000000000 >
0$
#2010000
0/
b10 ;
b1 <
1$
#2020000
0$
#2030000
b11 ;
b10 <
1$
#2040000
0$
#2050000
1/
b1 ;
b11 <
1$
#2060000
b100000000 3
b100000000 4
b100000000 >
0$
#2070000
0/
b10 ;
b1 <
1$
#2080000
0$
#2090000
b11 ;
b10 <
1$
#2100000
0$
#2110000
1/
b1 ;
b11 <
1$
#2120000
b10000000 3
b10000000 4
b10000000 >
0$
#2130000
0/
b10 ;
b1 <
1$
#2140000
0$
#2150000
b11 ;
b10 <
1$
#2160000
0$
#2170000
1/
b1 ;
b11 <
1$
#2180000
b1000000 3
b1000000 4
b1000000 >
0$
#2190000
0/
b10 ;
b1 <
1$
#2200000
0$
#2210000
b11 ;
b10 <
1$
#2220000
0$
#2230000
1/
b1 ;
b11 <
1$
#2240000
b100000 3
b100000 4
b100000 >
0$
#2250000
0/
b10 ;
b1 <
1$
#2260000
0$
#2270000
b11 ;
b10 <
1$
#2280000
0$
#2290000
1/
b1 ;
b11 <
1$
#2300000
b10000 3
b10000 4
b10000 >
0$
#2310000
0/
b10 ;
b1 <
1$
#2320000
0$
#2330000
b11 ;
b10 <
1$
#2340000
0$
#2350000
1/
b1 ;
b11 <
1$
#2360000
b1000 3
b1000 4
b1000 >
0$
#2370000
0/
b10 ;
b1 <
1$
#2380000
0$
#2390000
b11 ;
b10 <
1$
#2400000
0$
#2410000
1/
b1 ;
b11 <
1$
#2420000
b100 3
b100 4
b100 >
0$
#2430000
0/
b10 ;
b1 <
1$
#2440000
0$
#2450000
b11 ;
b10 <
1$
#2460000
0$
#2470000
1/
b1 ;
b11 <
1$
#2480000
b10 3
b10 4
b10 >
0$
#2490000
0/
b10 ;
b1 <
1$
#2500000
0$
#2510000
b11 ;
b10 <
1$
#2520000
0$
#2530000
1/
b1 ;
b11 <
1$
#2540000
1.
b1 3
b1 4
b1 >
0$
#2550000
0/
b10 ;
b1 <
1$
#2560000
0$
#2570000
b100 ;
b10 <
1$
#2580000
0$
#2590000
11
b11 ;
b100 <
1$
#2600000
b1 "
b1 ,
b1 2
b1 ?
0$
#2610000
1/
01
b1 ;
b11 <
1$
#2620000
0.
1-
b0 3
b0 4
b0 >
0$
#2630000
0/
b101 ;
b1 <
1$
#2640000
0$
#2650000
b100 (
1!
b0 ;
b101 <
1$
#2660000
0$
#2670000
10
0!
b0 <
1$
#2672000
b1000 @
b10000 *
b1010101010101010 )
b1010101010101010 A
#2680000
0-
b1000000000000000 3
b1000000000000000 4
b1000000000000000 >
b0 "
b0 ,
b0 2
b0 ?
0$
#2690000
1$
#2692000
b1 ;
1&
b1010101010101010 #
b1010101010101010 +
b1010101010101010 =
#2700000
b1010101010101010 3
b1010101010101010 4
b1010101010101010 >
0$
#2710000
00
b10 ;
b1 <
1$
#2712000
0&
#2720000
0$
#2730000
b11 ;
b10 <
1$
#2740000
0$
#2750000
1/
b1 ;
b11 <
1$
#2760000
1.
b101010101010101 3
b101010101010101 4
b101010101010101 >
0$
#2770000
0/
b10 ;
b1 <
1$
#2780000
0$
#2790000
b100 ;
b10 <
1$
#2800000
0$
#2810000
11
b11 ;
b100 <
1$
#2820000
b1 "
b1 ,
b1 2
b1 ?
0$
#2830000
1/
01
b1 ;
b11 <
1$
#2840000
0.
b10101010101010 3
b10101010101010 4
b10101010101010 >
0$
#2850000
0/
b10 ;
b1 <
1$
#2860000
0$
#2870000
b11 ;
b10 <
1$
#2880000
0$
#2890000
1/
b1 ;
b11 <
1$
#2900000
1.
b1010101010101 3
b1010101010101 4
b1010101010101 >
0$
#2910000
0/
b10 ;
b1 <
1$
#2920000
0$
#2930000
b100 ;
b10 <
1$
#2940000
0$
#2950000
11
b11 ;
b100 <
1$
#2960000
b10 "
b10 ,
b10 2
b10 ?
0$
#2970000
1/
01
b1 ;
b11 <
1$
#2980000
0.
b101010101010 3
b101010101010 4
b101010101010 >
0$
#2990000
0/
b10 ;
b1 <
1$
#3000000
0$
#3010000
b11 ;
b10 <
1$
#3020000
0$
#3030000
1/
b1 ;
b11 <
1$
#3040000
1.
b10101010101 3
b10101010101 4
b10101010101 >
0$
#3050000
0/
b10 ;
b1 <
1$
#3060000
0$
#3070000
b100 ;
b10 <
1$
#3080000
0$
#3090000
11
b11 ;
b100 <
1$
#3100000
b11 "
b11 ,
b11 2
b11 ?
0$
#3110000
1/
01
b1 ;
b11 <
1$
#3120000
0.
b1010101010 3
b1010101010 4
b1010101010 >
0$
#3130000
0/
b10 ;
b1 <
1$
#3140000
0$
#3150000
b11 ;
b10 <
1$
#3160000
0$
#3170000
1/
b1 ;
b11 <
1$
#3180000
1.
b101010101 3
b101010101 4
b101010101 >
0$
#3190000
0/
b10 ;
b1 <
1$
#3200000
0$
#3210000
b100 ;
b10 <
1$
#3220000
0$
#3230000
11
b11 ;
b100 <
1$
#3240000
b100 "
b100 ,
b100 2
b100 ?
0$
#3250000
1/
01
b1 ;
b11 <
1$
#3260000
0.
b10101010 3
b10101010 4
b10101010 >
0$
#3270000
0/
b10 ;
b1 <
1$
#3280000
0$
#3290000
b11 ;
b10 <
1$
#3300000
0$
#3310000
1/
b1 ;
b11 <
1$
#3320000
1.
b1010101 3
b1010101 4
b1010101 >
0$
#3330000
0/
b10 ;
b1 <
1$
#3340000
0$
#3350000
b100 ;
b10 <
1$
#3360000
0$
#3370000
11
b11 ;
b100 <
1$
#3380000
b101 "
b101 ,
b101 2
b101 ?
0$
#3390000
1/
01
b1 ;
b11 <
1$
#3400000
0.
b101010 3
b101010 4
b101010 >
0$
#3410000
0/
b10 ;
b1 <
1$
#3420000
0$
#3430000
b11 ;
b10 <
1$
#3440000
0$
#3450000
1/
b1 ;
b11 <
1$
#3460000
1.
b10101 3
b10101 4
b10101 >
0$
#3470000
0/
b10 ;
b1 <
1$
#3480000
0$
#3490000
b100 ;
b10 <
1$
#3500000
0$
#3510000
11
b11 ;
b100 <
1$
#3520000
b110 "
b110 ,
b110 2
b110 ?
0$
#3530000
1/
01
b1 ;
b11 <
1$
#3540000
0.
b1010 3
b1010 4
b1010 >
0$
#3550000
0/
b10 ;
b1 <
1$
#3560000
0$
#3570000
b11 ;
b10 <
1$
#3580000
0$
#3590000
1/
b1 ;
b11 <
1$
#3600000
1.
b101 3
b101 4
b101 >
0$
#3610000
0/
b10 ;
b1 <
1$
#3620000
0$
#3630000
b100 ;
b10 <
1$
#3640000
0$
#3650000
11
b11 ;
b100 <
1$
#3660000
b111 "
b111 ,
b111 2
b111 ?
0$
#3670000
1/
01
b1 ;
b11 <
1$
#3680000
0.
b10 3
b10 4
b10 >
0$
#3690000
0/
b10 ;
b1 <
1$
#3700000
0$
#3710000
b11 ;
b10 <
1$
#3720000
0$
#3730000
1/
b1 ;
b11 <
1$
#3740000
1.
b1 3
b1 4
b1 >
0$
#3750000
0/
b10 ;
b1 <
1$
#3760000
0$
#3770000
b100 ;
b10 <
1$
#3780000
0$
#3790000
11
b11 ;
b100 <
1$
#3800000
b1000 "
b1000 ,
b1000 2
b1000 ?
0$
#3810000
1/
01
b1 ;
b11 <
1$
#3820000
0.
1-
b0 3
b0 4
b0 >
0$
#3830000
0/
b101 ;
b1 <
1$
#3840000
0$
#3850000
b101 (
1!
b0 ;
b101 <
1$
#3860000
0$
#3870000
10
0!
b0 <
1$
#3872000
b10000 *
b11111111 )
b11111111 A
#3880000
0-
b1010101010101010 3
b1010101010101010 4
b1010101010101010 >
b0 "
b0 ,
b0 2
b0 ?
0$
#3890000
1$
#3892000
b1 ;
1&
b11111111 #
b11111111 +
b11111111 =
#3900000
1.
b11111111 3
b11111111 4
b11111111 >
0$
#3910000
00
b10 ;
b1 <
1$
#3912000
0&
#3920000
0$
#3930000
b100 ;
b10 <
1$
#3940000
0$
#3950000
11
b11 ;
b100 <
1$
#3960000
b1 "
b1 ,
b1 2
b1 ?
0$
#3970000
1/
01
b1 ;
b11 <
1$
#3980000
b1111111 3
b1111111 4
b1111111 >
0$
#3990000
0/
b10 ;
b1 <
1$
#4000000
0$
#4010000
b100 ;
b10 <
1$
#4020000
0$
#4030000
11
b11 ;
b100 <
1$
#4040000
b10 "
b10 ,
b10 2
b10 ?
0$
#4050000
1/
01
b1 ;
b11 <
1$
#4060000
b111111 3
b111111 4
b111111 >
0$
#4070000
0/
b10 ;
b1 <
1$
#4080000
0$
#4090000
b100 ;
b10 <
1$
#4100000
0$
#4110000
11
b11 ;
b100 <
1$
#4120000
b11 "
b11 ,
b11 2
b11 ?
0$
#4130000
1/
01
b1 ;
b11 <
1$
#4140000
b11111 3
b11111 4
b11111 >
0$
#4150000
0/
b10 ;
b1 <
1$
#4160000
0$
#4170000
b100 ;
b10 <
1$
#4180000
0$
#4190000
11
b11 ;
b100 <
1$
#4200000
b100 "
b100 ,
b100 2
b100 ?
0$
#4210000
1/
01
b1 ;
b11 <
1$
#4220000
b1111 3
b1111 4
b1111 >
0$
#4230000
0/
b10 ;
b1 <
1$
#4240000
0$
#4250000
b100 ;
b10 <
1$
#4260000
0$
#4270000
11
b11 ;
b100 <
1$
#4280000
b101 "
b101 ,
b101 2
b101 ?
0$
#4290000
1/
01
b1 ;
b11 <
1$
#4300000
b111 3
b111 4
b111 >
0$
#4310000
0/
b10 ;
b1 <
1$
#4320000
0$
#4330000
b100 ;
b10 <
1$
#4340000
0$
#4350000
11
b11 ;
b100 <
1$
#4360000
b110 "
b110 ,
b110 2
b110 ?
0$
#4370000
1/
01
b1 ;
b11 <
1$
#4380000
b11 3
b11 4
b11 >
0$
#4390000
0/
b10 ;
b1 <
1$
#4400000
0$
#4410000
b100 ;
b10 <
1$
#4420000
0$
#4430000
11
b11 ;
b100 <
1$
#4440000
b111 "
b111 ,
b111 2
b111 ?
0$
#4450000
1/
01
b1 ;
b11 <
1$
#4460000
b1 3
b1 4
b1 >
0$
#4470000
0/
b10 ;
b1 <
1$
#4480000
0$
#4490000
b100 ;
b10 <
1$
#4500000
0$
#4510000
11
b11 ;
b100 <
1$
#4520000
b1000 "
b1000 ,
b1000 2
b1000 ?
0$
#4530000
1/
01
b1 ;
b11 <
1$
#4540000
0.
1-
b0 3
b0 4
b0 >
0$
#4550000
0/
b101 ;
b1 <
1$
#4560000
0$
#4570000
b110 (
1!
b0 ;
b101 <
1$
#4580000
0$
#4590000
10
0!
b0 <
1$
#4592000
b101 @
b10000 *
b1001000110100 )
b1001000110100 A
#4600000
1.
0-
b11111111 3
b11111111 4
b11111111 >
b0 "
b0 ,
b0 2
b0 ?
0$
#4610000
1$
#4612000
b1 ;
1&
b1001000110100 #
b1001000110100 +
b1001000110100 =
#4620000
0.
b1001000110100 3
b1001000110100 4
b1001000110100 >
0$
#4630000
00
b10 ;
b1 <
1$
#4632000
0&
#4640000
0$
#4650000
b11 ;
b10 <
1$
#4660000
0$
#4670000
1/
b1 ;
b11 <
1$
#4680000
b100100011010 3
b100100011010 4
b100100011010 >
0$
#4690000
0/
b10 ;
b1 <
1$
#4700000
0$
#4710000
b11 ;
b10 <
1$
#4720000
0$
#4730000
1/
b1 ;
b11 <
1$
#4740000
1.
b10010001101 3
b10010001101 4
b10010001101 >
0$
#4750000
0/
b10 ;
b1 <
1$
#4760000
0$
#4770000
b100 ;
b10 <
1$
#4780000
0$
#4790000
11
b11 ;
b100 <
1$
#4800000
b1 "
b1 ,
b1 2
b1 ?
0$
#4810000
1/
01
b1 ;
b11 <
1$
#4820000
0.
b1001000110 3
b1001000110 4
b1001000110 >
0$
#4830000
0/
b10 ;
b1 <
1$
#4840000
0$
#4850000
b11 ;
b10 <
1$
#4860000
0$
#4870000
1/
b1 ;
b11 <
1$
#4880000
1.
b100100011 3
b100100011 4
b100100011 >
0$
#4890000
0/
b10 ;
b1 <
1$
#4900000
0$
#4910000
b100 ;
b10 <
1$
#4920000
0$
#4930000
11
b11 ;
b100 <
1$
#4940000
b10 "
b10 ,
b10 2
b10 ?
0$
#4950000
1/
01
b1 ;
b11 <
1$
#4960000
b10010001 3
b10010001 4
b10010001 >
0$
#4970000
0/
b10 ;
b1 <
1$
#4980000
0$
#4990000
b100 ;
b10 <
1$
#5000000
0$
#5010000
11
b11 ;
b100 <
1$
#5020000
b11 "
b11 ,
b11 2
b11 ?
0$
#5030000
1/
01
b1 ;
b11 <
1$
#5040000
0.
b1001000 3
b1001000 4
b1001000 >
0$
#5050000
0/
b10 ;
b1 <
1$
#5060000
0$
#5070000
b11 ;
b10 <
1$
#5080000
0$
#5090000
1/
b1 ;
b11 <
1$
#5100000
b100100 3
b100100 4
b100100 >
0$
#5110000
0/
b10 ;
b1 <
1$
#5120000
0$
#5130000
b11 ;
b10 <
1$
#5140000
0$
#5150000
1/
b1 ;
b11 <
1$
#5160000
b10010 3
b10010 4
b10010 >
0$
#5170000
0/
b10 ;
b1 <
1$
#5180000
0$
#5190000
b11 ;
b10 <
1$
#5200000
0$
#5210000
1/
b1 ;
b11 <
1$
#5220000
1.
b1001 3
b1001 4
b1001 >
0$
#5230000
0/
b10 ;
b1 <
1$
#5240000
0$
#5250000
b100 ;
b10 <
1$
#5260000
0$
#5270000
11
b11 ;
b100 <
1$
#5280000
b100 "
b100 ,
b100 2
b100 ?
0$
#5290000
1/
01
b1 ;
b11 <
1$
#5300000
0.
b100 3
b100 4
b100 >
0$
#5310000
0/
b10 ;
b1 <
1$
#5320000
0$
#5330000
b11 ;
b10 <
1$
