Entrega Final/multi/control_mult.v
module control_mult (
    input  wire clk,
    input  wire rst,     
    input  wire start,
    input  wire x,        
    input  wire z,        

    output reg  done,
    output reg  LD,
    output reg  SH,
    output reg  ADD,
    output reg  RST
);

    localparam [2:0] START_ST     = 3'b000;
    localparam [2:0] CHECK_B_ST   = 3'b001;
    localparam [2:0] CHECK_LSB_ST = 3'b010;
    localparam [2:0] ADD_ST       = 3'b011;
    localparam [2:0] SHIFT_ST     = 3'b100;
    localparam [2:0] DONE_ST      = 3'b101;

    reg [2:0] state, next_state;

    always @(posedge clk or posedge rst) begin
        if (rst)
            state <= START_ST;
        else
            state <= next_state;
    end

    always @(*) begin
        case (state)
            START_ST:     next_state = start ? CHECK_B_ST : START_ST;
            CHECK_B_ST:   next_state = z     ? DONE_ST    : CHECK_LSB_ST;
            CHECK_LSB_ST: next_state = x     ? ADD_ST     : SHIFT_ST;
            ADD_ST:       next_state = SHIFT_ST;
            SHIFT_ST:     next_state = CHECK_B_ST;
            DONE_ST:      next_state = START_ST;
            default:      next_state = START_ST;
        endcase
    end

    always @(*) begin
        done = 1'b0;
        LD   = 1'b0;
        SH   = 1'b0;
        ADD  = 1'b0;
        RST  = 1'b0;
        case (state)
            START_ST: begin
                LD  = 1'b1;
                RST = 1'b1;
            end
            CHECK_B_ST:   ; 
            CHECK_LSB_ST: ; 
            ADD_ST: begin
                ADD = 1'b1;
            end
            SHIFT_ST: begin
                SH = 1'b1;
            end
            DONE_ST: begin
                done = 1'b1;
            end
            default: ;
        endcase
    end

endmodule

Entrega Final/multi/acumulador.v
module acumulador (
    input  wire        clk,
    input  wire        add,    
    input  wire        rst,    
    input  wire [31:0] in_A,
    output reg  [31:0] P
);

    always @(negedge clk) begin
        if (rst)
            P <= 32'b0;
        else if (add)
            P <= P + in_A;
    end

endmodule

Entrega Final/multi/comparador.v
module comparador (
    input  wire [15:0] B,
    output wire         z,
    output wire         x
);

    assign z = (B == 16'b0);
    assign x = B[0];

endmodule

Entrega Final/multi/reg_B.v
module reg_B (
    input  wire        clk,
    input  wire        load,   
    input  wire        shift, 
    input  wire [15:0] in_B,
    output reg  [15:0] out_B,
    output wire         B_LSB
);

    always @(negedge clk) begin
        if (load)
            out_B <= in_B;
        else if (shift)
            out_B <= out_B >> 1;
    end

    assign B_LSB = out_B[0];

endmodule

Entrega Final/multi/reg_A.v
module reg_A (
    input  wire        clk,
    input  wire        load,   
    input  wire        shift,  
    input  wire [15:0] in_A,
    output reg  [31:0] out_A
);

    always @(negedge clk) begin
        if (load)
            out_A <= {16'b0, in_A};
        else if (shift)
            out_A <= out_A << 1;
    end

endmodule

Entrega Final/multi/multiplicador.v
module multiplicador (
    input  wire        clk,
    input  wire        rst,     
    input  wire        start,
    input  wire [15:0] A,
    input  wire [15:0] B,
    output wire [31:0] P,
    output wire         done
);

    // Senales de control
    wire w_LD, w_SH, w_ADD, w_RST;

    // Senales de estado 
    wire w_x, w_z, w_Blsb;

    // Buses internos del datapath 
    wire [31:0] w_Areg;
    wire [15:0] w_Breg;

    // DATAPATH

    reg_A u_reg_A (
        .clk   (clk),
        .load  (w_LD),
        .shift (w_SH),
        .in_A  (A),
        .out_A (w_Areg)
    );

    reg_B u_reg_B (
        .clk   (clk),
        .load  (w_LD),
        .shift (w_SH),
        .in_B  (B),
        .out_B (w_Breg),
        .B_LSB (w_Blsb)
    );

    comparador u_comp (
        .B (w_Breg),
        .z (w_z),
        .x (w_x)
    );

    acumulador u_acc (
        .clk  (clk),
        .add  (w_ADD),
        .rst  (w_RST),
        .in_A (w_Areg),
        .P    (P)
    );

    // CONTROL

    control_mult u_ctrl (
        .clk   (clk),
        .rst   (rst),
        .start (start),
        .x     (w_x),
        .z     (w_z),
        .done  (done),
        .LD    (w_LD),
        .SH    (w_SH),
        .ADD   (w_ADD),
        .RST   (w_RST)
    );

endmodule

Entrega Final/multi/multiplicador_tb.v
`timescale 1ns/1ps

module multiplicador_tb;

    reg         clk;
    reg         rst;
    reg         start;
    reg  [15:0] A;
    reg  [15:0] B;
    wire [31:0] P;
    wire        done;

    integer pruebas = 0;
    integer errores = 0;

    multiplicador uut (
        .clk   (clk),
        .rst   (rst),
        .start (start),
        .A     (A),
        .B     (B),
        .P     (P),
        .done  (done)
    );

    initial clk = 1'b0;
    always #10 clk = ~clk;

    task ejecutar_prueba(input [15:0] valA, input [15:0] valB);
        reg [31:0] esperado;
        begin
            esperado = valA * valB;

            @(posedge clk); #2;
            A     = valA;
            B     = valB;
            start = 1'b1;

            @(posedge clk); #2;
            start = 1'b0;

            wait (done == 1'b1);
            pruebas = pruebas + 1;

            if (P !== esperado) begin
                errores = errores + 1;
                $display("[%0t] FALLO -> A=%0d B=%0d : P=%0d (se esperaba %0d)",
                          $time, valA, valB, P, esperado);
            end else begin
                $display("[%0t] OK    -> A=%0d x B=%0d = %0d",
                          $time, valA, valB, P);
            end

            @(posedge clk); #2;
        end
    endtask

    initial begin
        $dumpfile("multiplicador_tb.vcd");
        $dumpvars(0, multiplicador_tb);

        rst   = 1'b1;
        start = 1'b0;
        A     = 16'd0;
        B     = 16'd0;

        #23;
        rst = 1'b0;

        ejecutar_prueba(16'd5,     16'd3);
        ejecutar_prueba(16'd0,     16'd10);
        ejecutar_prueba(16'd10,    16'd0);
        ejecutar_prueba(16'd1,     16'd1);
        ejecutar_prueba(16'd255,   16'd255);
        ejecutar_prueba(16'd12345, 16'd6789);
        ejecutar_prueba(16'd65535, 16'd65535);

        #40;
        $display("--------------------------------------------------");
        if (errores == 0)
            $display("RESULTADO: TODAS LAS PRUEBAS PASARON (%0d/%0d)", pruebas, pruebas);
        else
            $display("RESULTADO: %0d de %0d PRUEBAS FALLARON", errores, pruebas);
        $display("--------------------------------------------------");

        $finish;
    end

    initial begin
        #100000;
        $display("ERROR: TIMEOUT - la simulacion no termino a tiempo");
        $finish;
    end

endmodule

Entrega Final/multi/multiplicador_tb.vcd
$date
	Thu Jul 16 04:01:16 2026
$end
$version
	Icarus Verilog
$end
$timescale
	1ps
$end
$scope module multiplicador_tb $end
$var wire 1 ! done $end
$var wire 32 " P [31:0] $end
$var reg 16 # A [15:0] $end
$var reg 16 $ B [15:0] $end
$var reg 1 % clk $end
$var reg 1 & rst $end
$var reg 1 ' start $end
$var integer 32 ( errores [31:0] $end
$var integer 32 ) pruebas [31:0] $end
$scope module uut $end
$var wire 16 * A [15:0] $end
$var wire 16 + B [15:0] $end
$var wire 1 % clk $end
$var wire 1 & rst $end
$var wire 1 ' start $end
$var wire 1 , w_z $end
$var wire 1 - w_x $end
$var wire 1 . w_SH $end
$var wire 1 / w_RST $end
$var wire 1 0 w_LD $end
$var wire 16 1 w_Breg [15:0] $end
$var wire 1 2 w_Blsb $end
$var wire 32 3 w_Areg [31:0] $end
$var wire 1 4 w_ADD $end
$var wire 1 ! done $end
$var wire 32 5 P [31:0] $end
$scope module u_acc $end
$var wire 1 % clk $end
$var wire 1 / rst $end
$var wire 32 6 in_A [31:0] $end
$var wire 1 4 add $end
$var reg 32 7 P [31:0] $end
$upscope $end
$scope module u_comp $end
$var wire 1 , z $end
$var wire 1 - x $end
$var wire 16 8 B [15:0] $end
$upscope $end
$scope module u_ctrl $end
$var wire 1 % clk $end
$var wire 1 & rst $end
$var wire 1 ' start $end
$var wire 1 - x $end
$var wire 1 , z $end
$var parameter 3 9 ADD_ST $end
$var parameter 3 : CHECK_B_ST $end
$var parameter 3 ; CHECK_LSB_ST $end
$var parameter 3 < DONE_ST $end
$var parameter 3 = SHIFT_ST $end
$var parameter 3 > START_ST $end
$var reg 1 4 ADD $end
$var reg 1 0 LD $end
$var reg 1 / RST $end
$var reg 1 . SH $end
$var reg 1 ! done $end
$var reg 3 ? next_state [2:0] $end
$var reg 3 @ state [2:0] $end
$upscope $end
$scope module u_reg_A $end
$var wire 1 % clk $end
$var wire 16 A in_A [15:0] $end
$var wire 1 0 load $end
$var wire 1 . shift $end
$var reg 32 B out_A [31:0] $end
$upscope $end
$scope module u_reg_B $end
$var wire 1 % clk $end
$var wire 16 C in_B [15:0] $end
$var wire 1 0 load $end
$var wire 1 . shift $end
$var wire 1 2 B_LSB $end
$var reg 16 D out_B [15:0] $end
$upscope $end
$upscope $end
$scope task ejecutar_prueba $end
$var reg 32 E esperado [31:0] $end
$var reg 16 F valA [15:0] $end
$var reg 16 G valB [15:0] $end
$upscope $end
$upscope $end
$enddefinitions $end
$comment Show the parameter values. $end
$dumpall
b0 >
b100 =
b101 <
b10 ;
b1 :
b11 9
$end
#0
$dumpvars
bx G
bx F
bx E
bx D
b0 C
bx B
b0 A
b0 @
b0 ?
bx 8
bx 7
bx 6
bx 5
04
bx 3
x2
bx 1
10
1/
0.
x-
x,
b0 +
b0 *
b0 )
b0 (
0'
1&
0%
b0 $
b0 #
bx "
0!
$end
#10000
1%
#20000
02
0-
b0 "
b0 5
b0 7
1,
b0 1
b0 8
b0 D
b0 3
b0 6
b0 B
0%
#23000
b1111 E
b11 G
b101 F
0&
#30000
1%
#32000
b1 ?
1'
b11 $
b11 +
b11 C
b101 #
b101 *
b101 A
#40000
12
1-
b101 3
b101 6
b101 B
0,
b11 1
b11 8
b11 D
0%
#50000
0/
00
b10 ?
b1 @
1%
#52000
0'
#60000
0%
#70000
b11 ?
b10 @
1%
#80000
0%
#90000
14
b100 ?
b11 @
1%
#100000
b101 "
b101 5
b101 7
0%
#110000
1.
04
b1 ?
b100 @
1%
#120000
b1010 3
b1010 6
b1010 B
b1 1
b1 8
b1 D
0%
#130000
0.
b10 ?
b1 @
1%
#140000
0%
#150000
b11 ?
b10 @
1%
#160000
0%
#170000
14
b100 ?
b11 @
1%
#180000
b1111 "
b1111 5
b1111 7
0%
#190000
1.
04
b1 ?
b100 @
1%
#200000
02
0-
b10100 3
b10100 6
b10100 B
1,
b0 1
b0 8
b0 D
0%
#210000
0.
b101 ?
b1 @
1%
#220000
0%
#230000
b1 )
1!
b0 ?
b101 @
1%
#240000
0%
#250000
1/
10
0!
b0 @
1%
#252000
b0 E
b1010 G
b0 F
#260000
12
1-
b0 "
b0 5
b0 7
0,
b11 1
b11 8
b11 D
b101 3
b101 6
b101 B
0%
#270000
1%
#272000
b1 ?
1'
b1010 $
b1010 +
b1010 C
b0 #
b0 *
b0 A
#280000
02
0-
b0 3
b0 6
b0 B
b1010 1
b1010 8
b1010 D
0%
#290000
0/
00
b10 ?
b1 @
1%
#292000
0'
#300000
0%
#310000
b100 ?
b10 @
1%
#320000
0%
#330000
1.
b1 ?
b100 @
1%
#340000
12
1-
b101 1
b101 8
b101 D
0%
#350000
0.
b10 ?
b1 @
1%
#360000
0%
#370000
b11 ?
b10 @
1%
#380000
0%
#390000
14
b100 ?
b11 @
1%
#400000
0%
#410000
1.
04
b1 ?
b100 @
1%
#420000
02
0-
b10 1
b10 8
b10 D
0%
#430000
0.
b10 ?
b1 @
1%
#440000
0%
#450000
b100 ?
b10 @
1%
#460000
0%
#470000
1.
b1 ?
b100 @
1%
#480000
12
1-
b1 1
b1 8
b1 D
0%
#490000
0.
b10 ?
b1 @
1%
#500000
0%
#510000
b11 ?
b10 @
1%
#520000
0%
#530000
14
b100 ?
b11 @
1%
#540000
0%
#550000
1.
04
b1 ?
b100 @
1%
#560000
02
0-
1,
b0 1
b0 8
b0 D
0%
#570000
0.
b101 ?
b1 @
1%
#580000
0%
#590000
b10 )
1!
b0 ?
b101 @
1%
#600000
0%
#610000
1/
10
0!
b0 @
1%
#612000
b0 G
b1010 F
#620000
0,
b1010 1
b1010 8
b1010 D
0%
#630000
1%
#632000
b1 ?
1'
b0 $
b0 +
b0 C
b1010 #
b1010 *
b1010 A
#640000
b1010 3
b1010 6
b1010 B
1,
b0 1
b0 8
b0 D
0%
#650000
0/
00
b101 ?
b1 @
1%
#652000
0'
#660000
0%
#670000
b11 )
1!
b0 ?
b101 @
1%
#680000
0%
#690000
1/
10
0!
b0 @
1%
#692000
b1 E
b1 G
b1 F
#700000
0%
#710000
1%
#712000
b1 ?
1'
b1 $
b1 +
b1 C
b1 #
b1 *
b1 A
#720000
12
1-
b1 3
b1 6
b1 B
0,
b1 1
b1 8
b1 D
0%
#730000
0/
00
b10 ?
b1 @
1%
#732000
0'
#740000
0%
#750000
b11 ?
b10 @
1%
#760000
0%
#770000
14
b100 ?
b11 @
1%
#780000
b1 "
b1 5
b1 7
0%
#790000
1.
04
b1 ?
b100 @
1%
#800000
02
0-
b10 3
b10 6
b10 B
1,
b0 1
b0 8
b0 D
0%
#810000
0.
b101 ?
b1 @
1%
#820000
0%
#830000
b100 )
1!
b0 ?
b101 @
1%
#840000
0%
#850000
1/
10
0!
b0 @
1%
#852000
b1111111000000001 E
b11111111 G
b11111111 F
#860000
12
1-
b0 "
b0 5
b0 7
0,
b1 1
b1 8
b1 D
b1 3
b1 6
b1 B
0%
#870000
1%
#872000
b1 ?
1'
b11111111 $
b11111111 +
b11111111 C
b11111111 #
b11111111 *
b11111111 A
#880000
b11111111 3
b11111111 6
b11111111 B
b11111111 1
b11111111 8
b11111111 D
0%
#890000
0/
00
b10 ?
b1 @
1%
#892000
0'
#900000
0%
#910000
b11 ?
b10 @
1%
#920000
0%
#930000
14
b100 ?
b11 @
1%
#940000
b11111111 "
b11111111 5
b11111111 7
0%
#950000
1.
04
b1 ?
b100 @
1%
#960000
b111111110 3
b111111110 6
b111111110 B
b1111111 1
b1111111 8
b1111111 D
0%
#970000
0.
b10 ?
b1 @
1%
#980000
0%
#990000
b11 ?
b10 @
1%
#1000000
0%
#1010000
14
b100 ?
b11 @
1%
#1020000
b1011111101 "
b1011111101 5
b1011111101 7
0%
#1030000
1.
04
b1 ?
b100 @
1%
#1040000
b1111111100 3
b1111111100 6
b1111111100 B
b111111 1
b111111 8
b111111 D
0%
#1050000
0.
b10 ?
b1 @
1%
#1060000
0%
#1070000
b11 ?
b10 @
1%
#1080000
0%
#1090000
14
b100 ?
b11 @
1%
#1100000
b11011111001 "
b11011111001 5
b11011111001 7
0%
#1110000
1.
04
b1 ?
b100 @
1%
#1120000
b11111111000 3
b11111111000 6
b11111111000 B
b11111 1
b11111 8
b11111 D
0%
#1130000
0.
b10 ?
b1 @
1%
#1140000
0%
#1150000
b11 ?
b10 @
1%
#1160000
0%
#1170000
14
b100 ?
b11 @
1%
#1180000
b111011110001 "
b111011110001 5
b111011110001 7
0%
#1190000
1.
04
b1 ?
b100 @
1%
#1200000
b111111110000 3
b111111110000 6
b111111110000 B
b1111 1
b1111 8
b1111 D
0%
#1210000
0.
b10 ?
b1 @
1%
#1220000
0%
#1230000
b11 ?
b10 @
1%
#1240000
0%
#1250000
14
b100 ?
b11 @
1%
#1260000
b1111011100001 "
b1111011100001 5
b1111011100001 7
0%
#1270000
1.
04
b1 ?
b100 @
1%
#1280000
b1111111100000 3
b1111111100000 6
b1111111100000 B
b111 1
b111 8
b111 D
0%
#1290000
0.
b10 ?
b1 @
1%
#1300000
0%
#1310000
b11 ?
b10 @
1%
#1320000
0%
#1330000
14
b100 ?
b11 @
1%
#1340000
b11111011000001 "
b11111011000001 5
b11111011000001 7
0%
#1350000
1.
04
b1 ?
b100 @
1%
#1360000
b11111111000000 3
b11111111000000 6
b11111111000000 B
b11 1
b11 8
b11 D
0%
#1370000
0.
b10 ?
b1 @
1%
#1380000
0%
#1390000
b11 ?
b10 @
1%
#1400000
0%
#1410000
14
b100 ?
b11 @
1%
#1420000
b111111010000001 "
b111111010000001 5
b111111010000001 7
0%
#1430000
1.
04
b1 ?
b100 @
1%
#1440000
b111111110000000 3
b111111110000000 6
b111111110000000 B
b1 1
b1 8
b1 D
0%
#1450000
0.
b10 ?
b1 @
1%
#1460000
0%
#1470000
b11 ?
b10 @
1%
#1480000
0%
#1490000
14
b100 ?
b11 @
1%
#1500000
b1111111000000001 "
b1111111000000001 5
b1111111000000001 7
0%
#1510000
1.
04
b1 ?
b100 @
1%
#1520000
02
0-
b1111111100000000 3
b1111111100000000 6
b1111111100000000 B
1,
b0 1
b0 8
b0 D
0%
#1530000
0.
b101 ?
b1 @
1%
#1540000
0%
#1550000
b101 )
1!
b0 ?
b101 @
1%
#1560000
0%
#1570000
1/
10
0!
b0 @
1%
#1572000
b100111111101101011110011101 E
b1101010000101 G
b11000000111001 F
#1580000
12
1-
b0 "
b0 5
b0 7
0,
b11111111 1
b11111111 8
b11111111 D
b11111111 3
b11111111 6
b11111111 B
0%
#1590000
1%
#1592000
b1 ?
1'
b1101010000101 $
b1101010000101 +
b1101010000101 C
b11000000111001 #
b11000000111001 *
b11000000111001 A
#1600000
b11000000111001 3
b11000000111001 6
b11000000111001 B
b1101010000101 1
b1101010000101 8
b1101010000101 D
0%
#1610000
0/
00
b10 ?
b1 @
1%
#1612000
0'
#1620000
0%
#1630000
b11 ?
b10 @
1%
#1640000
0%
#1650000
14
b100 ?
b11 @
1%
#1660000
b11000000111001 "
b11000000111001 5
b11000000111001 7
0%
#1670000
1.
04
b1 ?
b100 @
1%
#1680000
02
0-
b110000001110010 3
b110000001110010 6
b110000001110010 B
b110101000010 1
b110101000010 8
b110101000010 D
0%
#1690000
0.
b10 ?
b1 @
1%
#1700000
0%
#1710000
b100 ?
b10 @
1%
#1720000
0%
#1730000
1.
b1 ?
b100 @
1%
#1740000
12
1-
b11010100001 1
b11010100001 8
b11010100001 D
b1100000011100100 3
b1100000011100100 6
b1100000011100100 B
0%
#1750000
0.
b10 ?
b1 @
1%
#1760000
0%
#1770000
b11 ?
b10 @
1%
#1780000
0%
#1790000
14
b100 ?
b11 @
1%
#1800000
b1111000100011101 "
b1111000100011101 5
b1111000100011101 7
0%
#1810000
1.
04
b1 ?
b100 @
1%
#1820000
02
0-
b1101010000 1
b1101010000 8
b1101010000 D
b11000000111001000 3
b11000000111001000 6
b11000000111001000 B
0%
#1830000
0.
b10 ?
b1 @
1%
#1840000
0%
#1850000
b100 ?
b10 @
1%
#1860000
0%
#1870000
1.
b1 ?
b100 @
1%
#1880000
b110000001110010000 3
b110000001110010000 6
b110000001110010000 B
b110101000 1
b110101000 8
b110101000 D
0%
#1890000
0.
b10 ?
b1 @
1%
#1900000
0%
#1910000
b100 ?
b10 @
1%
#1920000
0%
#1930000
1.
b1 ?
b100 @
1%
#1940000
b11010100 1
b11010100 8
b11010100 D
b1100000011100100000 3
b1100000011100100000 6
b1100000011100100000 B
0%
#1950000
0.
b10 ?
b1 @
1%
#1960000
0%
#1970000
b100 ?
b10 @
1%
#1980000
0%
#1990000
1.
b1 ?
b100 @
1%
#2000000
b11000000111001000000 3
b11000000111001000000 6
b11000000111001000000 B
b1101010 1
b1101010 8
b1101010 D
0%
#2010000
0.
b10 ?
b1 @
1%
#2020000
0%
#2030000
b100 ?
b10 @
1%
#2040000
0%
#2050000
1.
b1 ?
b100 @
1%
#2060000
12
1-
b110101 1
b110101 8
b110101 D
b110000001110010000000 3
b110000001110010000000 6
b110000001110010000000 B
0%
#2070000
0.
b10 ?
b1 @
1%
#2080000
0%
#2090000
b11 ?
b10 @
1%
#2100000
0%
#2110000
14
b100 ?
b11 @
1%
#2120000
b110010000110110011101 "
b110010000110110011101 5
b110010000110110011101 7
0%
#2130000
1.
04
b1 ?
b100 @
1%
#2140000
02
0-
b11010 1
b11010 8
b11010 D
b1100000011100100000000 3
b1100000011100100000000 6
b1100000011100100000000 B
0%
#2150000
0.
b10 ?
b1 @
1%
#2160000
0%
#2170000
b100 ?
b10 @
1%
#2180000
0%
#2190000
1.
b1 ?
b100 @
1%
#2200000
12
1-
b11000000111001000000000 3
b11000000111001000000000 6
b11000000111001000000000 B
b1101 1
b1101 8
b1101 D
0%
#2210000
0.
b10 ?
b1 @
1%
#2220000
0%
#2230000
b11 ?
b10 @
1%
#2240000
0%
#2250000
14
b100 ?
b11 @
1%
#2260000
b11110010111111110011101 "
b11110010111111110011101 5
b11110010111111110011101 7
0%
#2270000
1.
04
b1 ?
b100 @
1%
#2280000
02
0-
b110000001110010000000000 3
b110000001110010000000000 6
b110000001110010000000000 B
b110 1
b110 8
b110 D
0%
#2290000
0.
b10 ?
b1 @
1%
#2300000
0%
#2310000
b100 ?
b10 @
1%
#2320000
0%
#2330000
1.
b1 ?
b100 @
1%
#2340000
12
1-
b11 1
b11 8
b11 D
b1100000011100100000000000 3
b1100000011100100000000000 6
b1100000011100100000000000 B
0%
#2350000
0.
b10 ?
b1 @
1%
#2360000
0%
#2370000
b11 ?
b10 @
1%
#2380000
0%
#2390000
14
b100 ?
b11 @
1%
#2400000
b1111110110100011110011101 "
b1111110110100011110011101 5
b1111110110100011110011101 7
0%
#2410000
1.
04
b1 ?
b100 @
1%
#2420000
b1 1
b1 8
b1 D
b11000000111001000000000000 3
b11000000111001000000000000 6
b11000000111001000000000000 B
0%
#2430000
0.
b10 ?
b1 @
1%
#2440000
0%
#2450000
b11 ?
b10 @
1%
#2460000
0%
#2470000
14
b100 ?
b11 @
1%
#2480000
b100111111101101011110011101 "
b100111111101101011110011101 5
b100111111101101011110011101 7
0%
#2490000
1.
04
b1 ?
b100 @
1%
#2500000
02
0-
1,
b0 1
b0 8
b0 D
b110000001110010000000000000 3
b110000001110010000000000000 6
b110000001110010000000000000 B
0%
#2510000
0.
b101 ?
b1 @
1%
#2520000
0%
#2530000
b110 )
1!
b0 ?
b101 @
1%
#2540000
0%
#2550000
1/
10
0!
b0 @
1%
#2552000
b11111111111111100000000000000001 E
b1111111111111111 G
b1111111111111111 F
#2560000
12
1-
b11000000111001 3
b11000000111001 6
b11000000111001 B
0,
b1101010000101 1
b1101010000101 8
b1101010000101 D
b0 "
b0 5
b0 7
0%
#2570000
1%
#2572000
b1 ?
1'
b1111111111111111 $
b1111111111111111 +
b1111111111111111 C
b1111111111111111 #
b1111111111111111 *
b1111111111111111 A
#2580000
b1111111111111111 1
b1111111111111111 8
b1111111111111111 D
b1111111111111111 3
b1111111111111111 6
b1111111111111111 B
0%
#2590000
0/
00
b10 ?
b1 @
1%
#2592000
0'
#2600000
0%
#2610000
b11 ?
b10 @
1%
#2620000
0%
#2630000
14
b100 ?
b11 @
1%
#2640000
b1111111111111111 "
b1111111111111111 5
b1111111111111111 7
0%
#2650000
1.
04
b1 ?
b100 @
1%
#2660000
b111111111111111 1
b111111111111111 8
b111111111111111 D
b11111111111111110 3
b11111111111111110 6
b11111111111111110 B
0%
#2670000
0.
b10 ?
b1 @
1%
#2680000
0%
#2690000
b11 ?
b10 @
1%
#2700000
0%
#2710000
14
b100 ?
b11 @
1%
#2720000
b101111111111111101 "
b101111111111111101 5
b101111111111111101 7
0%
#2730000
1.
04
b1 ?
b100 @
1%
#2740000
b11111111111111 1
b11111111111111 8
b11111111111111 D
b111111111111111100 3
b111111111111111100 6
b111111111111111100 B
0%
#2750000
0.
b10 ?
b1 @
1%
#2760000
0%
#2770000
b11 ?
b10 @
1%
#2780000
0%
#2790000
14
b100 ?
b11 @
1%
#2800000
b1101111111111111001 "
b1101111111111111001 5
b1101111111111111001 7
0%
#2810000
1.
04
b1 ?
b100 @
1%
#2820000
b1111111111111 1
b1111111111111 8
b1111111111111 D
b1111111111111111000 3
b1111111111111111000 6
b1111111111111111000 B
0%
#2830000
0.
b10 ?
b1 @
1%
#2840000
0%
#2850000
b11 ?
b10 @
1%
#2860000
0%
#2870000
14
b100 ?
b11 @
1%
#2880000
b11101111111111110001 "
b11101111111111110001 5
b11101111111111110001 7
0%
#2890000
1.
04
b1 ?
b100 @
1%
#2900000
b111111111111 1
b111111111111 8
b111111111111 D
b11111111111111110000 3
b11111111111111110000 6
b11111111111111110000 B
0%
#2910000
0.
b10 ?
b1 @
1%
#2920000
0%
#2930000
b11 ?
b10 @
1%
#2940000
0%
#2950000
14
b100 ?
b11 @
1%
#2960000
b111101111111111100001 "
b111101111111111100001 5
b111101111111111100001 7
0%
#2970000
1.
04
b1 ?
b100 @
1%
#2980000
b11111111111 1
b11111111111 8
b11111111111 D
b111111111111111100000 3
b111111111111111100000 6
b111111111111111100000 B
0%
#2990000
0.
b10 ?
b1 @
1%
#3000000
0%
#3010000
b11 ?
b10 @
1%
#3020000
0%
#3030000
14
b100 ?
b11 @
1%
#3040000
b1111101111111111000001 "
b1111101111111111000001 5
b1111101111111111000001 7
0%
#3050000
1.
04
b1 ?
b100 @
1%
#3060000
b1111111111 1
b1111111111 8
b1111111111 D
b1111111111111111000000 3
b1111111111111111000000 6
b1111111111111111000000 B
0%
#3070000
0.
b10 ?
b1 @
1%
#3080000
0%
#3090000
b11 ?
b10 @
1%
#3100000
0%
#3110000
14
b100 ?
b11 @
1%
#3120000
b11111101111111110000001 "
b11111101111111110000001 5
b11111101111111110000001 7
0%
#3130000
1.
04
b1 ?
b100 @
1%
#3140000
b111111111 1
b111111111 8
b111111111 D
b11111111111111110000000 3
b11111111111111110000000 6
b11111111111111110000000 B
0%
#3150000
0.
b10 ?
b1 @
1%
#3160000
0%
#3170000
b11 ?
b10 @
1%
#3180000
0%
#3190000
14
b100 ?
b11 @
1%
#3200000
b111111101111111100000001 "
b111111101111111100000001 5
b111111101111111100000001 7
0%
#3210000
1.
04
b1 ?
b100 @
1%
#3220000
b11111111 1
b11111111 8
b11111111 D
b111111111111111100000000 3
b111111111111111100000000 6
b111111111111111100000000 B
0%
#3230000
0.
b10 ?
b1 @
1%
#3240000
0%
#3250000
b11 ?
b10 @
1%
#3260000
0%
#3270000
14
b100 ?
b11 @
1%
#3280000
b1111111101111111000000001 "
b1111111101111111000000001 5
b1111111101111111000000001 7
0%
#3290000
1.
04
b1 ?
b100 @
1%
#3300000
b1111111 1
b1111111 8
b1111111 D
b1111111111111111000000000 3
b1111111111111111000000000 6
b1111111111111111000000000 B
0%
#3310000
0.
b10 ?
b1 @
1%
#3320000
0%
#3330000
b11 ?
b10 @
1%
#3340000
0%
#3350000
14
b100 ?
b11 @
1%
#3360000
b11111111101111110000000001 "
b11111111101111110000000001 5
b11111111101111110000000001 7
0%
#3370000
1.
04
b1 ?
b100 @
1%
#3380000
b111111 1
b111111 8
b111111 D
b11111111111111110000000000 3
b11111111111111110000000000 6
b11111111111111110000000000 B
0%
#3390000
0.
b10 ?
b1 @
1%
#3400000
0%
#3410000
b11 ?
b10 @
1%
#3420000
0%
#3430000
14
b100 ?
b11 @
1%
#3440000
b111111111101111100000000001 "
b111111111101111100000000001 5
b111111111101111100000000001 7
0%
#3450000
1.
04
b1 ?
b100 @
1%
#3460000
b11111 1
b11111 8
b11111 D
b111111111111111100000000000 3
b111111111111111100000000000 6
b111111111111111100000000000 B
0%
#3470000
0.
b10 ?
b1 @
1%
#3480000
0%
#3490000
b11 ?
b10 @
1%
#3500000
0%
#3510000
14
b100 ?
b11 @
1%
#3520000
b1111111111101111000000000001 "
b1111111111101111000000000001 5
b1111111111101111000000000001 7
0%
#3530000
1.
04
b1 ?
b100 @
1%
#3540000
b1111 1
b1111 8
b1111 D
b1111111111111111000000000000 3
b1111111111111111000000000000 6
b1111111111111111000000000000 B
0%
#3550000
0.
b10 ?
b1 @
1%
#3560000
0%
#3570000
b11 ?
b10 @
1%
#3580000
0%
#3590000
14
b100 ?
b11 @
1%
#3600000
b11111111111101110000000000001 "
b11111111111101110000000000001 5
b11111111111101110000000000001 7
0%
#3610000
1.
04
b1 ?
b100 @
1%
#3620000
b111 1
b111 8
b111 D
b11111111111111110000000000000 3
b11111111111111110000000000000 6
b11111111111111110000000000000 B
0%
#3630000
0.
b10 ?
b1 @
1%
#3640000
0%
#3650000
b11 ?
b10 @
1%
#3660000
0%
#3670000
14
b100 ?
b11 @
1%
#3680000
b111111111111101100000000000001 "
b111111111111101100000000000001 5
b111111111111101100000000000001 7
0%
#3690000
1.
04
b1 ?
b100 @
1%
#3700000
b11 1
b11 8
b11 D
b111111111111111100000000000000 3
b111111111111111100000000000000 6
b111111111111111100000000000000 B
0%
#3710000
0.
b10 ?
b1 @
1%
#3720000
0%
#3730000
b11 ?
b10 @
1%
#3740000
0%
#3750000
14
b100 ?
b11 @
1%
#3760000
b1111111111111101000000000000001 "
b1111111111111101000000000000001 5
b1111111111111101000000000000001 7
0%
#3770000
1.
04
b1 ?
b100 @
1%
#3780000
b1 1
b1 8
b1 D
b1111111111111111000000000000000 3
b1111111111111111000000000000000 6
b1111111111111111000000000000000 B
0%
#3790000
0.
b10 ?
b1 @
1%
#3800000
0%
#3810000
b11 ?
b10 @
1%
#3820000
0%
#3830000
14
b100 ?
b11 @
1%
#3840000
b11111111111111100000000000000001 "
b11111111111111100000000000000001 5
b11111111111111100000000000000001 7
0%
#3850000
1.
04
b1 ?
b100 @
1%
#3860000
02
0-
1,
b0 1
b0 8
b0 D
b11111111111111110000000000000000 3
b11111111111111110000000000000000 6
b11111111111111110000000000000000 B
0%
#3870000
0.
b101 ?
b1 @
1%
#3880000
0%
#3890000
b111 )
1!
b0 ?
b101 @
1%
#3900000
0%
#3910000
1/
10
0!
b0 @
1%
#3920000
12
1-
b1111111111111111 3
b1111111111111111 6
b1111111111111111 B
0,
b1111111111111111 1
b1111111111111111 8
b1111111111111111 D
b0 "
b0 5
b0 7
0%
