Entrega Final/raiz/control_raiz.v
`timescale 1ns/1ps
module control_raiz (
    input  wire clk,
    input  wire rst,     
    input  wire start,
    input  wire z,       

    output reg  done,
    output reg  LD,
    output reg  ADD,
    output reg  INC
);

    localparam [1:0] START_ST = 2'b00;
    localparam [1:0] CHECK_ST = 2'b01;
    localparam [1:0] ADD_ST   = 2'b10;
    localparam [1:0] DONE_ST  = 2'b11;

    reg [1:0] state, next_state;

    always @(posedge clk or posedge rst) begin
        if (rst)
            state <= START_ST;
        else
            state <= next_state;
    end

    always @(*) begin
        case (state)
            START_ST: next_state = start ? CHECK_ST : START_ST;
            CHECK_ST: next_state = z     ? ADD_ST    : DONE_ST;
            ADD_ST:   next_state = CHECK_ST;
            DONE_ST:  next_state = START_ST;
            default:  next_state = START_ST;
        endcase
    end

    always @(*) begin
        done = 1'b0;
        LD   = 1'b0;
        ADD  = 1'b0;
        INC  = 1'b0;
        case (state)
            START_ST: begin
                LD = 1'b1;
            end
            CHECK_ST: ; // solo decide
            ADD_ST: begin
                ADD = 1'b1;
                INC = 1'b1;
            end
            DONE_ST: begin
                done = 1'b1;
            end
            default: ;
        endcase
    end

endmodule

Entrega Final/raiz/reg_Q.v
`timescale 1ns/1ps
module reg_Q_raiz (
    input  wire        clk,
    input  wire        ld,    
    input  wire        inc,   
    output reg  [15:0] Q
);

    always @(negedge clk) begin
        if (ld)
            Q <= 16'h0000;
        else if (inc)
            Q <= Q + 16'h0001;
    end

endmodule

Entrega Final/raiz/comp.v
`timescale 1ns/1ps
module comp_raiz (
    input  wire [15:0] X,
    input  wire [15:0] D,
    output wire         z
);

    assign z = (X >= D);

endmodule

Entrega Final/raiz/reg_X_acc.v
`timescale 1ns/1ps
module reg_X_acc (
    input  wire        clk,
    input  wire        ld,    
    input  wire        add,   
    input  wire [15:0] in_X,  
    input  wire [15:0] D,
    output reg  [15:0] X
);

    always @(negedge clk) begin
        if (ld)
            X <= in_X;
        else if (add)
            X <= X - D;
    end

endmodule

Entrega Final/raiz/reg_D.v
`timescale 1ns/1ps
module reg_D (
    input  wire        clk,
    input  wire        add,    
    input  wire        ld,     
    output reg  [15:0] D
);

    always @(negedge clk) begin
        if (ld)
            D <= 16'h0001;
        else if (add)
            D <= D + 16'h0002;
    end

endmodule

Entrega Final/raiz/raiz_cuadrada.v
`timescale 1ns/1ps
module raiz_cuadrada (
    input  wire        clk,
    input  wire        rst,    
    input  wire        start,
    input  wire [15:0] X,
    output wire [15:0] Q,      
    output wire [15:0] Residuo, 
    output wire         done
);

    //Senales de control 
    wire w_LD, w_ADD, w_INC;

    // Senal de estado (Datapath -> Control) ----
    wire w_z;

    //Buses internos del datapath ----
    wire [15:0] w_Xacc;
    wire [15:0] w_D;
    wire [15:0] w_Q;

    // DATAPATH

    reg_D u_reg_D (
        .clk (clk),
        .add (w_ADD),
        .ld  (w_LD),
        .D   (w_D)
    );

    reg_X_acc u_reg_Xacc (
        .clk  (clk),
        .ld   (w_LD),
        .add  (w_ADD),
        .in_X (X),
        .D    (w_D),
        .X    (w_Xacc)
    );

    comp_raiz u_comp (
        .X (w_Xacc),
        .D (w_D),
        .z (w_z)
    );

    reg_Q_raiz u_reg_Q (
        .clk (clk),
        .ld  (w_LD),
        .inc (w_INC),
        .Q   (w_Q)
    );

    // CONTROl

    control_raiz u_ctrl (
        .clk   (clk),
        .rst   (rst),
        .start (start),
        .z     (w_z),
        .done  (done),
        .LD    (w_LD),
        .ADD   (w_ADD),
        .INC   (w_INC)
    );

    // ---- Salidas ----
    assign Q       = w_Q;
    assign Residuo = w_Xacc;

endmodule

Entrega Final/raiz/raiz_cuadrada_tb.v
`timescale 1ns/1ps

module raiz_cuadrada_tb;

    reg         clk;
    reg         rst;
    reg         start;
    reg  [15:0] Xin;
    wire [15:0] Q;
    wire [15:0] Residuo;
    wire        done;

    integer pruebas = 0;
    integer errores = 0;

    raiz_cuadrada uut (
        .clk     (clk),
        .rst     (rst),
        .start   (start),
        .X       (Xin),
        .Q       (Q),
        .Residuo (Residuo),
        .done    (done)
    );

    initial clk = 1'b0;
    always #10 clk = ~clk;

    function [15:0] raiz_entera;
        input [15:0] val;
        reg [15:0] n;
        begin
            n = 16'd0;
            while ((n + 16'd1) * (n + 16'd1) <= val)
                n = n + 16'd1;
            raiz_entera = n;
        end
    endfunction

    task ejecutar_prueba(input [15:0] valX);
        reg [15:0] esperadoQ;
        reg [15:0] esperadoR;
        begin
            esperadoQ = raiz_entera(valX);
            esperadoR = valX - (esperadoQ * esperadoQ);

            @(posedge clk); #2;
            Xin   = valX;
            start = 1'b1;

            @(posedge clk); #2;
            start = 1'b0;

            wait (done == 1'b1);
            pruebas = pruebas + 1;

            if (Q !== esperadoQ || Residuo !== esperadoR) begin
                errores = errores + 1;
                $display("[%0t] FALLO -> X=%0d : Q=%0d Residuo=%0d (se esperaba Q=%0d R=%0d)",
                          $time, valX, Q, Residuo, esperadoQ, esperadoR);
            end else begin
                $display("[%0t] OK    -> raiz(%0d) = %0d, residuo %0d",
                          $time, valX, Q, Residuo);
            end

            @(posedge clk); #2;
        end
    endtask

    // Secuencia principal 
    initial begin
        $dumpfile("raiz_cuadrada_tb.vcd");
        $dumpvars(0, raiz_cuadrada_tb);

        rst   = 1'b1;
        start = 1'b0;
        Xin   = 16'd0;

        #23;
        rst = 1'b0;

        ejecutar_prueba(16'd0);
        ejecutar_prueba(16'd1);
        ejecutar_prueba(16'd10);
        ejecutar_prueba(16'd16);
        ejecutar_prueba(16'd99);
        ejecutar_prueba(16'd255);
        ejecutar_prueba(16'd2000);

        #40;
        $display("--------------------------------------------------");
        if (errores == 0)
            $display("RESULTADO: TODAS LAS PRUEBAS PASARON (%0d/%0d)", pruebas, pruebas);
        else
            $display("RESULTADO: %0d de %0d PRUEBAS FALLARON", errores, pruebas);
        $display("--------------------------------------------------");

        $finish;
    end

    initial begin
        #200000;
        $display("ERROR: TIMEOUT - la simulacion no termino a tiempo");
        $finish;
    end

endmodule

Entrega Final/raiz/raiz_cuadrada_tb.vcd
$date
	Thu Jul 16 04:01:23 2026
$end
$version
	Icarus Verilog
$end
$timescale
	1ps
$end
$scope module raiz_cuadrada_tb $end
$var wire 1 ! done $end
$var wire 16 " Residuo [15:0] $end
$var wire 16 # Q [15:0] $end
$var reg 16 $ Xin [15:0] $end
$var reg 1 % clk $end
$var reg 1 & rst $end
$var reg 1 ' start $end
$var integer 32 ( errores [31:0] $end
$var integer 32 ) pruebas [31:0] $end
$scope function raiz_entera $end
$var reg 16 * n [15:0] $end
$var reg 16 + val [15:0] $end
$upscope $end
$scope module uut $end
$var wire 16 , Q [15:0] $end
$var wire 16 - Residuo [15:0] $end
$var wire 16 . X [15:0] $end
$var wire 1 % clk $end
$var wire 1 & rst $end
$var wire 1 ' start $end
$var wire 1 / w_z $end
$var wire 16 0 w_Xacc [15:0] $end
$var wire 16 1 w_Q [15:0] $end
$var wire 1 2 w_LD $end
$var wire 1 3 w_INC $end
$var wire 16 4 w_D [15:0] $end
$var wire 1 5 w_ADD $end
$var wire 1 ! done $end
$scope module u_comp $end
$var wire 1 / z $end
$var wire 16 6 X [15:0] $end
$var wire 16 7 D [15:0] $end
$upscope $end
$scope module u_ctrl $end
$var wire 1 % clk $end
$var wire 1 & rst $end
$var wire 1 ' start $end
$var wire 1 / z $end
$var parameter 2 8 ADD_ST $end
$var parameter 2 9 CHECK_ST $end
$var parameter 2 : DONE_ST $end
$var parameter 2 ; START_ST $end
$var reg 1 5 ADD $end
$var reg 1 3 INC $end
$var reg 1 2 LD $end
$var reg 1 ! done $end
$var reg 2 < next_state [1:0] $end
$var reg 2 = state [1:0] $end
$upscope $end
$scope module u_reg_D $end
$var wire 1 5 add $end
$var wire 1 % clk $end
$var wire 1 2 ld $end
$var reg 16 > D [15:0] $end
$upscope $end
$scope module u_reg_Q $end
$var wire 1 % clk $end
$var wire 1 3 inc $end
$var wire 1 2 ld $end
$var reg 16 ? Q [15:0] $end
$upscope $end
$scope module u_reg_Xacc $end
$var wire 16 @ D [15:0] $end
$var wire 1 5 add $end
$var wire 1 % clk $end
$var wire 16 A in_X [15:0] $end
$var wire 1 2 ld $end
$var reg 16 B X [15:0] $end
$upscope $end
$upscope $end
$scope task ejecutar_prueba $end
$var reg 16 C esperadoQ [15:0] $end
$var reg 16 D esperadoR [15:0] $end
$var reg 16 E valX [15:0] $end
$upscope $end
$upscope $end
$enddefinitions $end
$comment Show the parameter values. $end
$dumpall
b0 ;
b11 :
b1 9
b10 8
$end
#0
$dumpvars
bx E
bx D
bx C
bx B
b0 A
bx @
bx ?
bx >
b0 =
b0 <
bx 7
bx 6
05
bx 4
03
12
bx 1
bx 0
x/
b0 .
bx -
bx ,
bx +
bx *
b0 )
b0 (
0'
1&
0%
b0 $
bx #
bx "
0!
$end
#10000
1%
#20000
b0 #
b0 ,
b0 1
b0 ?
0/
b0 "
b0 -
b0 0
b0 6
b0 B
b1 4
b1 7
b1 >
b1 @
0%
#23000
b0 D
b0 C
b0 *
b0 +
b0 E
0&
#30000
1%
#32000
b1 <
1'
#40000
0%
#50000
02
b11 <
b1 =
1%
#52000
0'
#60000
0%
#70000
b1 )
1!
b0 <
b11 =
1%
#80000
0%
#90000
12
0!
b0 =
1%
#92000
b1 C
b1 *
b1 +
b1 E
#100000
0%
#110000
1%
#112000
b1 <
1'
b1 $
b1 .
b1 A
#120000
1/
b1 "
b1 -
b1 0
b1 6
b1 B
0%
#130000
02
b10 <
b1 =
1%
#132000
0'
#140000
0%
#150000
13
15
b1 <
b10 =
1%
#160000
b11 4
b11 7
b11 >
b11 @
0/
b0 "
b0 -
b0 0
b0 6
b0 B
b1 #
b1 ,
b1 1
b1 ?
0%
#170000
03
05
b11 <
b1 =
1%
#180000
0%
#190000
b10 )
1!
b0 <
b11 =
1%
#200000
0%
#210000
12
0!
b0 =
1%
#212000
b1 D
b11 C
b11 *
b1010 +
b1010 E
#220000
b0 #
b0 ,
b0 1
b0 ?
1/
b1 "
b1 -
b1 0
b1 6
b1 B
b1 4
b1 7
b1 >
b1 @
0%
#230000
1%
#232000
b1 <
1'
b1010 $
b1010 .
b1010 A
#240000
b1010 "
b1010 -
b1010 0
b1010 6
b1010 B
0%
#250000
02
b10 <
b1 =
1%
#252000
0'
#260000
0%
#270000
13
15
b1 <
b10 =
1%
#280000
b11 4
b11 7
b11 >
b11 @
b1001 "
b1001 -
b1001 0
b1001 6
b1001 B
b1 #
b1 ,
b1 1
b1 ?
0%
#290000
03
05
b10 <
b1 =
1%
#300000
0%
#310000
13
15
b1 <
b10 =
1%
#320000
b101 4
b101 7
b101 >
b101 @
b110 "
b110 -
b110 0
b110 6
b110 B
b10 #
b10 ,
b10 1
b10 ?
0%
#330000
03
05
b10 <
b1 =
1%
#340000
0%
#350000
13
15
b1 <
b10 =
1%
#360000
b111 4
b111 7
b111 >
b111 @
0/
b1 "
b1 -
b1 0
b1 6
b1 B
b11 #
b11 ,
b11 1
b11 ?
0%
#370000
03
05
b11 <
b1 =
1%
#380000
0%
#390000
b11 )
1!
b0 <
b11 =
1%
#400000
0%
#410000
12
0!
b0 =
1%
#412000
b0 D
b100 C
b100 *
b10000 +
b10000 E
#420000
b0 #
b0 ,
b0 1
b0 ?
b1010 "
b1010 -
b1010 0
b1010 6
b1010 B
1/
b1 4
b1 7
b1 >
b1 @
0%
#430000
1%
#432000
b1 <
1'
b10000 $
b10000 .
b10000 A
#440000
b10000 "
b10000 -
b10000 0
b10000 6
b10000 B
0%
#450000
02
b10 <
b1 =
1%
#452000
0'
#460000
0%
#470000
13
15
b1 <
b10 =
1%
#480000
b11 4
b11 7
b11 >
b11 @
b1111 "
b1111 -
b1111 0
b1111 6
b1111 B
b1 #
b1 ,
b1 1
b1 ?
0%
#490000
03
05
b10 <
b1 =
1%
#500000
0%
#510000
13
15
b1 <
b10 =
1%
#520000
b101 4
b101 7
b101 >
b101 @
b1100 "
b1100 -
b1100 0
b1100 6
b1100 B
b10 #
b10 ,
b10 1
b10 ?
0%
#530000
03
05
b10 <
b1 =
1%
#540000
0%
#550000
13
15
b1 <
b10 =
1%
#560000
b111 4
b111 7
b111 >
b111 @
b111 "
b111 -
b111 0
b111 6
b111 B
b11 #
b11 ,
b11 1
b11 ?
0%
#570000
03
05
b10 <
b1 =
1%
#580000
0%
#590000
13
15
b1 <
b10 =
1%
#600000
b1001 4
b1001 7
b1001 >
b1001 @
0/
b0 "
b0 -
b0 0
b0 6
b0 B
b100 #
b100 ,
b100 1
b100 ?
0%
#610000
03
05
b11 <
b1 =
1%
#620000
0%
#630000
b100 )
1!
b0 <
b11 =
1%
#640000
0%
#650000
12
0!
b0 =
1%
#652000
b10010 D
b1001 C
b1001 *
b1100011 +
b1100011 E
#660000
b0 #
b0 ,
b0 1
b0 ?
1/
b10000 "
b10000 -
b10000 0
b10000 6
b10000 B
b1 4
b1 7
b1 >
b1 @
0%
#670000
1%
#672000
b1 <
1'
b1100011 $
b1100011 .
b1100011 A
#680000
b1100011 "
b1100011 -
b1100011 0
b1100011 6
b1100011 B
0%
#690000
02
b10 <
b1 =
1%
#692000
0'
#700000
0%
#710000
13
15
b1 <
b10 =
1%
#720000
b11 4
b11 7
b11 >
b11 @
b1100010 "
b1100010 -
b1100010 0
b1100010 6
b1100010 B
b1 #
b1 ,
b1 1
b1 ?
0%
#730000
03
05
b10 <
b1 =
1%
#740000
0%
#750000
13
15
b1 <
b10 =
1%
#760000
b101 4
b101 7
b101 >
b101 @
b1011111 "
b1011111 -
b1011111 0
b1011111 6
b1011111 B
b10 #
b10 ,
b10 1
b10 ?
0%
#770000
03
05
b10 <
b1 =
1%
#780000
0%
#790000
13
15
b1 <
b10 =
1%
#800000
b111 4
b111 7
b111 >
b111 @
b1011010 "
b1011010 -
b1011010 0
b1011010 6
b1011010 B
b11 #
b11 ,
b11 1
b11 ?
0%
#810000
03
05
b10 <
b1 =
1%
#820000
0%
#830000
13
15
b1 <
b10 =
1%
#840000
b1001 4
b1001 7
b1001 >
b1001 @
b1010011 "
b1010011 -
b1010011 0
b1010011 6
b1010011 B
b100 #
b100 ,
b100 1
b100 ?
0%
#850000
03
05
b10 <
b1 =
1%
#860000
0%
#870000
13
15
b1 <
b10 =
1%
#880000
b1011 4
b1011 7
b1011 >
b1011 @
b1001010 "
b1001010 -
b1001010 0
b1001010 6
b1001010 B
b101 #
b101 ,
b101 1
b101 ?
0%
#890000
03
05
b10 <
b1 =
1%
#900000
0%
#910000
13
15
b1 <
b10 =
1%
#920000
b1101 4
b1101 7
b1101 >
b1101 @
b111111 "
b111111 -
b111111 0
b111111 6
b111111 B
b110 #
b110 ,
b110 1
b110 ?
0%
#930000
03
05
b10 <
b1 =
1%
#940000
0%
#950000
13
15
b1 <
b10 =
1%
#960000
b1111 4
b1111 7
b1111 >
b1111 @
b110010 "
b110010 -
b110010 0
b110010 6
b110010 B
b111 #
b111 ,
b111 1
b111 ?
0%
#970000
03
05
b10 <
b1 =
1%
#980000
0%
#990000
13
15
b1 <
b10 =
1%
#1000000
b10001 4
b10001 7
b10001 >
b10001 @
b100011 "
b100011 -
b100011 0
b100011 6
b100011 B
b1000 #
b1000 ,
b1000 1
b1000 ?
0%
#1010000
03
05
b10 <
b1 =
1%
#1020000
0%
#1030000
13
15
b1 <
b10 =
1%
#1040000
0/
b10011 4
b10011 7
b10011 >
b10011 @
b10010 "
b10010 -
b10010 0
b10010 6
b10010 B
b1001 #
b1001 ,
b1001 1
b1001 ?
0%
#1050000
03
05
b11 <
b1 =
1%
#1060000
0%
#1070000
b101 )
1!
b0 <
b11 =
1%
#1080000
0%
#1090000
12
0!
b0 =
1%
#1092000
b11110 D
b1111 C
b1111 *
b11111111 +
b11111111 E
#1100000
b0 #
b0 ,
b0 1
b0 ?
b1100011 "
b1100011 -
b1100011 0
b1100011 6
b1100011 B
1/
b1 4
b1 7
b1 >
b1 @
0%
#1110000
1%
#1112000
b1 <
1'
b11111111 $
b11111111 .
b11111111 A
#1120000
b11111111 "
b11111111 -
b11111111 0
b11111111 6
b11111111 B
0%
#1130000
02
b10 <
b1 =
1%
#1132000
0'
#1140000
0%
#1150000
13
15
b1 <
b10 =
1%
#1160000
b11 4
b11 7
b11 >
b11 @
b11111110 "
b11111110 -
b11111110 0
b11111110 6
b11111110 B
b1 #
b1 ,
b1 1
b1 ?
0%
#1170000
03
05
b10 <
b1 =
1%
#1180000
0%
#1190000
13
15
b1 <
b10 =
1%
#1200000
b101 4
b101 7
b101 >
b101 @
b11111011 "
b11111011 -
b11111011 0
b11111011 6
b11111011 B
b10 #
b10 ,
b10 1
b10 ?
0%
#1210000
03
05
b10 <
b1 =
1%
#1220000
0%
#1230000
13
15
b1 <
b10 =
1%
#1240000
b111 4
b111 7
b111 >
b111 @
b11110110 "
b11110110 -
b11110110 0
b11110110 6
b11110110 B
b11 #
b11 ,
b11 1
b11 ?
0%
#1250000
03
05
b10 <
b1 =
1%
#1260000
0%
#1270000
13
15
b1 <
b10 =
1%
#1280000
b1001 4
b1001 7
b1001 >
b1001 @
b11101111 "
b11101111 -
b11101111 0
b11101111 6
b11101111 B
b100 #
b100 ,
b100 1
b100 ?
0%
#1290000
03
05
b10 <
b1 =
1%
#1300000
0%
#1310000
13
15
b1 <
b10 =
1%
#1320000
b1011 4
b1011 7
b1011 >
b1011 @
b11100110 "
b11100110 -
b11100110 0
b11100110 6
b11100110 B
b101 #
b101 ,
b101 1
b101 ?
0%
#1330000
03
05
b10 <
b1 =
1%
#1340000
0%
#1350000
13
15
b1 <
b10 =
1%
#1360000
b1101 4
b1101 7
b1101 >
b1101 @
b11011011 "
b11011011 -
b11011011 0
b11011011 6
b11011011 B
b110 #
b110 ,
b110 1
b110 ?
0%
#1370000
03
05
b10 <
b1 =
1%
#1380000
0%
#1390000
13
15
b1 <
b10 =
1%
#1400000
b1111 4
b1111 7
b1111 >
b1111 @
b11001110 "
b11001110 -
b11001110 0
b11001110 6
b11001110 B
b111 #
b111 ,
b111 1
b111 ?
0%
#1410000
03
05
b10 <
b1 =
1%
#1420000
0%
#1430000
13
15
b1 <
b10 =
1%
#1440000
b10001 4
b10001 7
b10001 >
b10001 @
b10111111 "
b10111111 -
b10111111 0
b10111111 6
b10111111 B
b1000 #
b1000 ,
b1000 1
b1000 ?
0%
#1450000
03
05
b10 <
b1 =
1%
#1460000
0%
#1470000
13
15
b1 <
b10 =
1%
#1480000
b10011 4
b10011 7
b10011 >
b10011 @
b10101110 "
b10101110 -
b10101110 0
b10101110 6
b10101110 B
b1001 #
b1001 ,
b1001 1
b1001 ?
0%
#1490000
03
05
b10 <
b1 =
1%
#1500000
0%
#1510000
13
15
b1 <
b10 =
1%
#1520000
b10101 4
b10101 7
b10101 >
b10101 @
b10011011 "
b10011011 -
b10011011 0
b10011011 6
b10011011 B
b1010 #
b1010 ,
b1010 1
b1010 ?
0%
#1530000
03
05
b10 <
b1 =
1%
#1540000
0%
#1550000
13
15
b1 <
b10 =
1%
#1560000
b10111 4
b10111 7
b10111 >
b10111 @
b10000110 "
b10000110 -
b10000110 0
b10000110 6
b10000110 B
b1011 #
b1011 ,
b1011 1
b1011 ?
0%
#1570000
03
05
b10 <
b1 =
1%
#1580000
0%
#1590000
13
15
b1 <
b10 =
1%
#1600000
b11001 4
b11001 7
b11001 >
b11001 @
b1101111 "
b1101111 -
b1101111 0
b1101111 6
b1101111 B
b1100 #
b1100 ,
b1100 1
b1100 ?
0%
#1610000
03
05
b10 <
b1 =
1%
#1620000
0%
#1630000
13
15
b1 <
b10 =
1%
#1640000
b11011 4
b11011 7
b11011 >
b11011 @
b1010110 "
b1010110 -
b1010110 0
b1010110 6
b1010110 B
b1101 #
b1101 ,
b1101 1
b1101 ?
0%
#1650000
03
05
b10 <
b1 =
1%
#1660000
0%
#1670000
13
15
b1 <
b10 =
1%
#1680000
b11101 4
b11101 7
b11101 >
b11101 @
b111011 "
b111011 -
b111011 0
b111011 6
b111011 B
b1110 #
b1110 ,
b1110 1
b1110 ?
0%
#1690000
03
05
b10 <
b1 =
1%
#1700000
0%
#1710000
13
15
b1 <
b10 =
1%
#1720000
0/
b11111 4
b11111 7
b11111 >
b11111 @
b11110 "
b11110 -
b11110 0
b11110 6
b11110 B
b1111 #
b1111 ,
b1111 1
b1111 ?
0%
#1730000
03
05
b11 <
b1 =
1%
#1740000
0%
#1750000
b110 )
1!
b0 <
b11 =
1%
#1760000
0%
#1770000
12
0!
b0 =
1%
#1772000
b1000000 D
b101100 C
b101100 *
b11111010000 +
b11111010000 E
#1780000
b0 #
b0 ,
b0 1
b0 ?
b11111111 "
b11111111 -
b11111111 0
b11111111 6
b11111111 B
1/
b1 4
b1 7
b1 >
b1 @
0%
#1790000
1%
#1792000
b1 <
1'
b11111010000 $
b11111010000 .
b11111010000 A
#1800000
b11111010000 "
b11111010000 -
b11111010000 0
b11111010000 6
b11111010000 B
0%
#1810000
02
b10 <
b1 =
1%
#1812000
0'
#1820000
0%
#1830000
13
15
b1 <
b10 =
1%
#1840000
b11 4
b11 7
b11 >
b11 @
b11111001111 "
b11111001111 -
b11111001111 0
b11111001111 6
b11111001111 B
b1 #
b1 ,
b1 1
b1 ?
0%
#1850000
03
05
b10 <
b1 =
1%
#1860000
0%
#1870000
13
15
b1 <
b10 =
1%
#1880000
b101 4
b101 7
b101 >
b101 @
b11111001100 "
b11111001100 -
b11111001100 0
b11111001100 6
b11111001100 B
b10 #
b10 ,
b10 1
b10 ?
0%
#1890000
03
05
b10 <
b1 =
1%
#1900000
0%
#1910000
13
15
b1 <
b10 =
1%
#1920000
b111 4
b111 7
b111 >
b111 @
b11111000111 "
b11111000111 -
b11111000111 0
b11111000111 6
b11111000111 B
b11 #
b11 ,
b11 1
b11 ?
0%
#1930000
03
05
b10 <
b1 =
1%
#1940000
0%
#1950000
13
15
b1 <
b10 =
1%
#1960000
b1001 4
b1001 7
b1001 >
b1001 @
b11111000000 "
b11111000000 -
b11111000000 0
b11111000000 6
b11111000000 B
b100 #
b100 ,
b100 1
b100 ?
0%
#1970000
03
05
b10 <
b1 =
1%
#1980000
0%
#1990000
13
15
b1 <
b10 =
1%
#2000000
b1011 4
b1011 7
b1011 >
b1011 @
b11110110111 "
b11110110111 -
b11110110111 0
b11110110111 6
b11110110111 B
b101 #
b101 ,
b101 1
b101 ?
0%
#2010000
03
05
b10 <
b1 =
1%
#2020000
0%
#2030000
13
15
b1 <
b10 =
1%
#2040000
b1101 4
b1101 7
b1101 >
b1101 @
b11110101100 "
b11110101100 -
b11110101100 0
b11110101100 6
b11110101100 B
b110 #
b110 ,
b110 1
b110 ?
0%
#2050000
03
05
b10 <
b1 =
1%
#2060000
0%
#2070000
13
15
b1 <
b10 =
1%
#2080000
b1111 4
b1111 7
b1111 >
b1111 @
b11110011111 "
b11110011111 -
b11110011111 0
b11110011111 6
b11110011111 B
b111 #
b111 ,
b111 1
b111 ?
0%
#2090000
03
05
b10 <
b1 =
1%
#2100000
0%
#2110000
13
15
b1 <
b10 =
1%
#2120000
b10001 4
b10001 7
b10001 >
b10001 @
b11110010000 "
b11110010000 -
b11110010000 0
b11110010000 6
b11110010000 B
b1000 #
b1000 ,
b1000 1
b1000 ?
0%
#2130000
03
05
b10 <
b1 =
1%
#2140000
0%
#2150000
13
15
b1 <
b10 =
1%
#2160000
b10011 4
b10011 7
b10011 >
b10011 @
b11101111111 "
b11101111111 -
b11101111111 0
b11101111111 6
b11101111111 B
b1001 #
b1001 ,
b1001 1
b1001 ?
0%
#2170000
03
05
b10 <
b1 =
1%
#2180000
0%
#2190000
13
15
b1 <
b10 =
1%
#2200000
b10101 4
b10101 7
b10101 >
b10101 @
b11101101100 "
b11101101100 -
b11101101100 0
b11101101100 6
b11101101100 B
b1010 #
b1010 ,
b1010 1
b1010 ?
0%
#2210000
03
05
b10 <
b1 =
1%
#2220000
0%
#2230000
13
15
b1 <
b10 =
1%
#2240000
b10111 4
b10111 7
b10111 >
b10111 @
b11101010111 "
b11101010111 -
b11101010111 0
b11101010111 6
b11101010111 B
b1011 #
b1011 ,
b1011 1
b1011 ?
0%
#2250000
03
05
b10 <
b1 =
1%
#2260000
0%
#2270000
13
15
b1 <
b10 =
1%
#2280000
b11001 4
b11001 7
b11001 >
b11001 @
b11101000000 "
b11101000000 -
b11101000000 0
b11101000000 6
b11101000000 B
b1100 #
b1100 ,
b1100 1
b1100 ?
0%
#2290000
03
05
b10 <
b1 =
1%
#2300000
0%
#2310000
13
15
b1 <
b10 =
1%
#2320000
b11011 4
b11011 7
b11011 >
b11011 @
b11100100111 "
b11100100111 -
b11100100111 0
b11100100111 6
b11100100111 B
b1101 #
b1101 ,
b1101 1
b1101 ?
0%
#2330000
03
05
b10 <
b1 =
1%
#2340000
0%
#2350000
13
15
b1 <
b10 =
1%
#2360000
b11101 4
b11101 7
b11101 >
b11101 @
b11100001100 "
b11100001100 -
b11100001100 0
b11100001100 6
b11100001100 B
b1110 #
b1110 ,
b1110 1
b1110 ?
0%
#2370000
03
05
b10 <
b1 =
1%
#2380000
0%
#2390000
13
15
b1 <
b10 =
1%
#2400000
b11111 4
b11111 7
b11111 >
b11111 @
b11011101111 "
b11011101111 -
b11011101111 0
b11011101111 6
b11011101111 B
b1111 #
b1111 ,
b1111 1
b1111 ?
0%
#2410000
03
05
b10 <
b1 =
1%
#2420000
0%
#2430000
13
15
b1 <
b10 =
1%
#2440000
b100001 4
b100001 7
b100001 >
b100001 @
b11011010000 "
b11011010000 -
b11011010000 0
b11011010000 6
b11011010000 B
b10000 #
b10000 ,
b10000 1
b10000 ?
0%
#2450000
03
05
b10 <
b1 =
1%
#2460000
0%
#2470000
13
15
b1 <
b10 =
1%
#2480000
b100011 4
b100011 7
b100011 >
b100011 @
b11010101111 "
b11010101111 -
b11010101111 0
b11010101111 6
b11010101111 B
b10001 #
b10001 ,
b10001 1
b10001 ?
0%
#2490000
03
05
b10 <
b1 =
1%
#2500000
0%
#2510000
13
15
b1 <
b10 =
1%
#2520000
b100101 4
b100101 7
b100101 >
b100101 @
b11010001100 "
b11010001100 -
b11010001100 0
b11010001100 6
b11010001100 B
b10010 #
b10010 ,
b10010 1
b10010 ?
0%
#2530000
03
05
b10 <
b1 =
1%
#2540000
0%
#2550000
13
15
b1 <
b10 =
1%
#2560000
b100111 4
b100111 7
b100111 >
b100111 @
b11001100111 "
b11001100111 -
b11001100111 0
b11001100111 6
b11001100111 B
b10011 #
b10011 ,
b10011 1
b10011 ?
0%
#2570000
03
05
b10 <
b1 =
1%
#2580000
0%
#2590000
13
15
b1 <
b10 =
1%
#2600000
b101001 4
b101001 7
b101001 >
b101001 @
b11001000000 "
b11001000000 -
b11001000000 0
b11001000000 6
b11001000000 B
b10100 #
b10100 ,
b10100 1
b10100 ?
0%
#2610000
03
05
b10 <
b1 =
1%
#2620000
0%
#2630000
13
15
b1 <
b10 =
1%
#2640000
b101011 4
b101011 7
b101011 >
b101011 @
b11000010111 "
b11000010111 -
b11000010111 0
b11000010111 6
b11000010111 B
b10101 #
b10101 ,
b10101 1
b10101 ?
0%
#2650000
03
05
b10 <
b1 =
1%
#2660000
0%
#2670000
13
15
b1 <
b10 =
1%
#2680000
b101101 4
b101101 7
b101101 >
b101101 @
b10111101100 "
b10111101100 -
b10111101100 0
b10111101100 6
b10111101100 B
b10110 #
b10110 ,
b10110 1
b10110 ?
0%
#2690000
03
05
b10 <
b1 =
1%
#2700000
0%
#2710000
13
15
b1 <
b10 =
1%
#2720000
b101111 4
b101111 7
b101111 >
b101111 @
b10110111111 "
b10110111111 -
b10110111111 0
b10110111111 6
b10110111111 B
b10111 #
b10111 ,
b10111 1
b10111 ?
0%
#2730000
03
05
b10 <
b1 =
1%
#2740000
0%
#2750000
13
15
b1 <
b10 =
1%
#2760000
b110001 4
b110001 7
b110001 >
b110001 @
b10110010000 "
b10110010000 -
b10110010000 0
b10110010000 6
b10110010000 B
b11000 #
b11000 ,
b11000 1
b11000 ?
0%
#2770000
03
05
b10 <
b1 =
1%
#2780000
0%
#2790000
13
15
b1 <
b10 =
1%
#2800000
b110011 4
b110011 7
b110011 >
b110011 @
b10101011111 "
b10101011111 -
b10101011111 0
b10101011111 6
b10101011111 B
b11001 #
b11001 ,
b11001 1
b11001 ?
0%
#2810000
03
05
b10 <
b1 =
1%
#2820000
0%
#2830000
13
15
b1 <
b10 =
1%
#2840000
b110101 4
b110101 7
b110101 >
b110101 @
b10100101100 "
b10100101100 -
b10100101100 0
b10100101100 6
b10100101100 B
b11010 #
b11010 ,
b11010 1
b11010 ?
0%
#2850000
03
05
b10 <
b1 =
1%
#2860000
0%
#2870000
13
15
b1 <
b10 =
1%
#2880000
b110111 4
b110111 7
b110111 >
b110111 @
b10011110111 "
b10011110111 -
b10011110111 0
b10011110111 6
b10011110111 B
b11011 #
b11011 ,
b11011 1
b11011 ?
0%
#2890000
03
05
b10 <
b1 =
1%
#2900000
0%
#2910000
13
15
b1 <
b10 =
1%
#2920000
b111001 4
b111001 7
b111001 >
b111001 @
b10011000000 "
b10011000000 -
b10011000000 0
b10011000000 6
b10011000000 B
b11100 #
b11100 ,
b11100 1
b11100 ?
0%
#2930000
03
05
b10 <
b1 =
1%
#2940000
0%
#2950000
13
15
b1 <
b10 =
1%
#2960000
b111011 4
b111011 7
b111011 >
b111011 @
b10010000111 "
b10010000111 -
b10010000111 0
b10010000111 6
b10010000111 B
b11101 #
b11101 ,
b11101 1
b11101 ?
0%
#2970000
03
05
b10 <
b1 =
1%
#2980000
0%
#2990000
13
15
b1 <
b10 =
1%
